[{"kod":"538043","nazev":"Babice","okres":"Praha-východ","kraj":"Středočeský kraj","obyvatel":1311,"mandatu":11,"okresNuts":"CZ0209","volicu":909,"ucast":33.88,"platneHlasy":2371,"strany":[{"nazev":"Za Babice","hlasy":2371,"mandaty":11,"kandidatu":11}]},{"kod":"538051","nazev":"Bašť","okres":"Praha-východ","kraj":"Středočeský kraj","obyvatel":2851,"mandatu":15,"okresNuts":"CZ0209","volicu":1689,"ucast":51.81,"platneHlasy":12036,"strany":[{"nazev":"Bašť – obec pro náš život","hlasy":3357,"mandaty":4,"kandidatu":15},{"nazev":"Konečně společně","hlasy":4144,"mandaty":6,"kandidatu":15},{"nazev":"NEZÁVISLÍ KANDIDÁTI PRO BUDOUCNOST BAŠTĚ A STAN","hlasy":2638,"mandaty":3,"kandidatu":15},{"nazev":"Občanská demokratická strana","hlasy":1897,"mandaty":2,"kandidatu":15}]},{"kod":"534684","nazev":"Borek","okres":"Praha-východ","kraj":"Středočeský kraj","obyvatel":311,"mandatu":7,"okresNuts":"CZ0209","volicu":251,"ucast":63.75,"platneHlasy":879,"strany":[{"nazev":"Sdružení nezávislých kandidátů obce Borek","hlasy":879,"mandaty":7,"kandidatu":9}]},{"kod":"538086","nazev":"Bořanovice","okres":"Praha-východ","kraj":"Středočeský kraj","obyvatel":908,"mandatu":9,"okresNuts":"CZ0209","volicu":652,"ucast":45.25,"platneHlasy":1613,"strany":[{"nazev":"Za obec Bořanovice","hlasy":1613,"mandaty":9,"kandidatu":9}]},{"kod":"538094","nazev":"Brandýs nad Labem-Stará Boleslav","okres":"Praha-východ","kraj":"Středočeský kraj","obyvatel":18755,"mandatu":21,"okresNuts":"CZ0209","volicu":13435,"ucast":44.09,"platneHlasy":111962,"strany":[{"nazev":"Podpora občanů","hlasy":23182,"mandaty":4,"kandidatu":21},{"nazev":"Občanská demokratická strana","hlasy":15142,"mandaty":3,"kandidatu":21},{"nazev":"Česká pirátská strana","hlasy":10392,"mandaty":2,"kandidatu":21},{"nazev":"ZDRAVÍ SPORT PROSPERITA","hlasy":10083,"mandaty":2,"kandidatu":21},{"nazev":"VY JSTE MĚSTO","hlasy":21001,"mandaty":4,"kandidatu":21},{"nazev":"NAŠE DVOJMĚSTÍ","hlasy":32162,"mandaty":6,"kandidatu":21}]},{"kod":"538108","nazev":"Brázdim","okres":"Praha-východ","kraj":"Středočeský kraj","obyvatel":684,"mandatu":9,"okresNuts":"CZ0209","volicu":556,"ucast":63.49,"platneHlasy":2933,"strany":[{"nazev":"Sdružení nezávislých kandidátů - Brázdim 2022","hlasy":1251,"mandaty":4,"kandidatu":9},{"nazev":"Sdružení nezávislých kandidátů OBCE BRÁZDIM","hlasy":1682,"mandaty":5,"kandidatu":9}]},{"kod":"564869","nazev":"Březí","okres":"Praha-východ","kraj":"Středočeský kraj","obyvatel":619,"mandatu":7,"okresNuts":"CZ0209","volicu":433,"ucast":68.59,"platneHlasy":1948,"strany":[{"nazev":"Za udržitelný rozvoj obce Březí","hlasy":751,"mandaty":3,"kandidatu":7},{"nazev":"Sdružení nezávislých kandidátů Společně PRO Březí","hlasy":1197,"mandaty":4,"kandidatu":7}]},{"kod":"538132","nazev":"Čelákovice","okres":"Praha-východ","kraj":"Středočeský kraj","obyvatel":12008,"mandatu":21,"okresNuts":"CZ0209","volicu":8921,"ucast":49.18,"platneHlasy":85469,"strany":[{"nazev":"Občanská demokratická strana","hlasy":47329,"mandaty":13,"kandidatu":21},{"nazev":"Koalice hnutí ANO a hnutí Zdraví sport prosperita","hlasy":17480,"mandaty":4,"kandidatu":21},{"nazev":"PRO ČELÁKOVICE, STAROSTOVÉ A NEZÁVISLÍ","hlasy":10628,"mandaty":3,"kandidatu":21},{"nazev":"ČELem","hlasy":4217,"mandaty":0,"kandidatu":21},{"nazev":"SPOLEČNĚ pro Čelákovice (TOP 09, KDU-ČSL, LES)","hlasy":5815,"mandaty":1,"kandidatu":21}]},{"kod":"533254","nazev":"Černé Voděrady","okres":"Praha-východ","kraj":"Středočeský kraj","obyvatel":340,"mandatu":7,"okresNuts":"CZ0209","volicu":285,"ucast":54.04,"platneHlasy":994,"strany":[{"nazev":"Za rozvoj obce","hlasy":935,"mandaty":7,"kandidatu":7},{"nazev":"SPORTOVCI PRO VODĚRADY","hlasy":59,"mandaty":0,"kandidatu":4}]},{"kod":"538141","nazev":"Čestlice","okres":"Praha-východ","kraj":"Středočeský kraj","obyvatel":684,"mandatu":9,"okresNuts":"CZ0209","volicu":547,"ucast":69.65,"platneHlasy":3322,"strany":[{"nazev":"Společně pro Čestlice","hlasy":2924,"mandaty":8,"kandidatu":9},{"nazev":"ČESTLICE PRO BUDOUCNOST","hlasy":398,"mandaty":1,"kandidatu":9}]},{"kod":"565008","nazev":"Dobročovice","okres":"Praha-východ","kraj":"Středočeský kraj","obyvatel":332,"mandatu":7,"okresNuts":"CZ0209","volicu":236,"ucast":41.53,"platneHlasy":513,"strany":[{"nazev":"Nezávislí z Dobročovic","hlasy":513,"mandaty":7,"kandidatu":9}]},{"kod":"538167","nazev":"Dobřejovice","okres":"Praha-východ","kraj":"Středočeský kraj","obyvatel":1210,"mandatu":9,"okresNuts":"CZ0209","volicu":812,"ucast":65.52,"platneHlasy":4588,"strany":[{"nazev":"Dobřejováci","hlasy":878,"mandaty":1,"kandidatu":9},{"nazev":"Moderní Dobřejovice","hlasy":2647,"mandaty":6,"kandidatu":9},{"nazev":"Za slušné Dobřejovice","hlasy":588,"mandaty":1,"kandidatu":9},{"nazev":"Společně, ale jinak","hlasy":475,"mandaty":1,"kandidatu":8}]},{"kod":"564885","nazev":"Doubek","okres":"Praha-východ","kraj":"Středočeský kraj","obyvatel":464,"mandatu":7,"okresNuts":"CZ0209","volicu":352,"ucast":50.57,"platneHlasy":851,"strany":[{"nazev":"MICHAL GLASER","hlasy":98,"mandaty":1,"kandidatu":1},{"nazev":"LENKA ČÍŽKOVÁ","hlasy":112,"mandaty":1,"kandidatu":1},{"nazev":"JINDŘICH ŠTENCL","hlasy":94,"mandaty":1,"kandidatu":1},{"nazev":"RADKA RYBOLOVÁ","hlasy":118,"mandaty":1,"kandidatu":1},{"nazev":"Michaela MECEROVÁ","hlasy":95,"mandaty":1,"kandidatu":1},{"nazev":"Renáta Kuprová","hlasy":147,"mandaty":1,"kandidatu":1},{"nazev":"Mgr. ALEŠ VYKYDAL","hlasy":80,"mandaty":0,"kandidatu":1},{"nazev":"Bc. DANA ČADILOVÁ","hlasy":107,"mandaty":1,"kandidatu":1}]},{"kod":"538191","nazev":"Dřevčice","okres":"Praha-východ","kraj":"Středočeský kraj","obyvatel":768,"mandatu":11,"okresNuts":"CZ0209","volicu":567,"ucast":60.32,"platneHlasy":2772,"strany":[{"nazev":"Ing. Radislav Vilím","hlasy":121,"mandaty":0,"kandidatu":1},{"nazev":"Sdružení nezávislých kandidátů pro Dřevčice","hlasy":2515,"mandaty":11,"kandidatu":11},{"nazev":"Tomáš Kropáček","hlasy":136,"mandaty":0,"kandidatu":1}]},{"kod":"534781","nazev":"Dřísy","okres":"Praha-východ","kraj":"Středočeský kraj","obyvatel":985,"mandatu":9,"okresNuts":"CZ0209","volicu":756,"ucast":60.05,"platneHlasy":3835,"strany":[{"nazev":"SDRUŽENÍ NEZÁVISLÝCH KANDIDÁTŮ DŘÍSY","hlasy":2041,"mandaty":5,"kandidatu":9},{"nazev":"Občanská demokratická strana","hlasy":524,"mandaty":1,"kandidatu":9},{"nazev":"Žijeme Dřísy","hlasy":1270,"mandaty":3,"kandidatu":9}]},{"kod":"564915","nazev":"Herink","okres":"Praha-východ","kraj":"Středočeský kraj","obyvatel":981,"mandatu":9,"okresNuts":"CZ0209","volicu":581,"ucast":59.72,"platneHlasy":3006,"strany":[{"nazev":"SNK Jdeme dál","hlasy":1975,"mandaty":6,"kandidatu":9},{"nazev":"STAN A OBČANÉ HERINKU","hlasy":1031,"mandaty":3,"kandidatu":9}]},{"kod":"565989","nazev":"Hlavenec","okres":"Praha-východ","kraj":"Středočeský kraj","obyvatel":445,"mandatu":5,"okresNuts":"CZ0209","volicu":283,"ucast":64.66,"platneHlasy":802,"strany":[{"nazev":"Sdružení nezávislých kandidátů Hlavenec","hlasy":802,"mandaty":5,"kandidatu":6}]},{"kod":"538221","nazev":"Horoušany","okres":"Praha-východ","kraj":"Středočeský kraj","obyvatel":1579,"mandatu":9,"okresNuts":"CZ0209","volicu":1125,"ucast":53.69,"platneHlasy":4698,"strany":[{"nazev":"Pro naše Horoušany a Horoušánky","hlasy":1689,"mandaty":4,"kandidatu":9},{"nazev":"Jana Klopfštocková, nezávislý kandidát","hlasy":118,"mandaty":0,"kandidatu":1},{"nazev":"Sdružení za Horoušany a Horoušánky","hlasy":2051,"mandaty":4,"kandidatu":9},{"nazev":"Občanská demokratická strana","hlasy":840,"mandaty":1,"kandidatu":8}]},{"kod":"538230","nazev":"Hovorčovice","okres":"Praha-východ","kraj":"Středočeský kraj","obyvatel":2496,"mandatu":11,"okresNuts":"CZ0209","volicu":1782,"ucast":57.91,"platneHlasy":10423,"strany":[{"nazev":"SNK Pro Hovorčovice","hlasy":2822,"mandaty":3,"kandidatu":11},{"nazev":"Společně pro Hovorčovice","hlasy":7429,"mandaty":8,"kandidatu":11},{"nazev":"Za otevřenější Hovorčovice","hlasy":172,"mandaty":0,"kandidatu":2}]},{"kod":"538248","nazev":"Hrusice","okres":"Praha-východ","kraj":"Středočeský kraj","obyvatel":882,"mandatu":9,"okresNuts":"CZ0209","volicu":662,"ucast":58.01,"platneHlasy":3203,"strany":[{"nazev":"Sdružení nezávislých kandidátů","hlasy":2663,"mandaty":8,"kandidatu":9},{"nazev":"SDRUŽENÍ NEZÁVISLÝCH KANDIDÁTŮ HRUSICKÝCH SPOLKŮ","hlasy":540,"mandaty":1,"kandidatu":9}]},{"kod":"538256","nazev":"Husinec","okres":"Praha-východ","kraj":"Středočeský kraj","obyvatel":1497,"mandatu":9,"okresNuts":"CZ0209","volicu":1079,"ucast":58.11,"platneHlasy":5201,"strany":[{"nazev":"Žijeme v Husinci a Řeži","hlasy":1643,"mandaty":3,"kandidatu":8},{"nazev":"NEZÁVISLÍ","hlasy":889,"mandaty":1,"kandidatu":8},{"nazev":"Společně","hlasy":2669,"mandaty":5,"kandidatu":9}]},{"kod":"538264","nazev":"Jenštejn","okres":"Praha-východ","kraj":"Středočeský kraj","obyvatel":1360,"mandatu":9,"okresNuts":"CZ0209","volicu":806,"ucast":36.97,"platneHlasy":1919,"strany":[{"nazev":"ZMĚNA PRO JENŠTEJN","hlasy":1919,"mandaty":9,"kandidatu":9}]},{"kod":"533378","nazev":"Jevany","okres":"Praha-východ","kraj":"Středočeský kraj","obyvatel":783,"mandatu":9,"okresNuts":"CZ0209","volicu":605,"ucast":70.74,"platneHlasy":3693,"strany":[{"nazev":"Občanská demokratická strana","hlasy":798,"mandaty":2,"kandidatu":9},{"nazev":"JEVAŇÁCI","hlasy":920,"mandaty":2,"kandidatu":9},{"nazev":"JEVANSKÉ FÓRUM","hlasy":902,"mandaty":2,"kandidatu":9},{"nazev":"TOP 09","hlasy":762,"mandaty":2,"kandidatu":9},{"nazev":"SDRUŽENÍ PRO JEVANY","hlasy":311,"mandaty":1,"kandidatu":9}]},{"kod":"538272","nazev":"Jirny","okres":"Praha-východ","kraj":"Středočeský kraj","obyvatel":2988,"mandatu":13,"okresNuts":"CZ0209","volicu":2073,"ucast":56.15,"platneHlasy":13700,"strany":[{"nazev":"Pro Jirny a Nové Jirny","hlasy":3675,"mandaty":4,"kandidatu":13},{"nazev":"Sousedé","hlasy":3336,"mandaty":3,"kandidatu":13},{"nazev":"Nezávislí s podporou TOP09","hlasy":1765,"mandaty":2,"kandidatu":13},{"nazev":"Sdružení Nezávislých Kandidátů Jirny a Nové Jirny","hlasy":4330,"mandaty":4,"kandidatu":13},{"nazev":"Občanská demokratická strana","hlasy":594,"mandaty":0,"kandidatu":11}]},{"kod":"538281","nazev":"Kaliště","okres":"Praha-východ","kraj":"Středočeský kraj","obyvatel":339,"mandatu":7,"okresNuts":"CZ0209","volicu":254,"ucast":64.57,"platneHlasy":1024,"strany":[{"nazev":"Žijeme zde společně","hlasy":744,"mandaty":5,"kandidatu":9},{"nazev":"Sdružení nezávislých","hlasy":280,"mandaty":2,"kandidatu":9}]},{"kod":"538299","nazev":"Kamenice","okres":"Praha-východ","kraj":"Středočeský kraj","obyvatel":4782,"mandatu":15,"okresNuts":"CZ0209","volicu":3572,"ucast":48.04,"platneHlasy":23664,"strany":[{"nazev":"PRO KAMENICI","hlasy":9954,"mandaty":6,"kandidatu":15},{"nazev":"„KAM21“","hlasy":13710,"mandaty":9,"kandidatu":15}]},{"kod":"564974","nazev":"Káraný","okres":"Praha-východ","kraj":"Středočeský kraj","obyvatel":779,"mandatu":7,"okresNuts":"CZ0209","volicu":637,"ucast":41.6,"platneHlasy":1014,"strany":[{"nazev":"Sdružení nezávislých kandidátů Káraný","hlasy":1014,"mandaty":7,"kandidatu":7}]},{"kod":"538311","nazev":"Klecany","okres":"Praha-východ","kraj":"Středočeský kraj","obyvatel":3601,"mandatu":15,"okresNuts":"CZ0209","volicu":2479,"ucast":49.94,"platneHlasy":14752,"strany":[{"nazev":"Občanská demokratická strana","hlasy":9457,"mandaty":10,"kandidatu":15},{"nazev":"SDRUŽENÍ NEZÁVISLÝCH KANDIDÁTŮ A HNUTÍ STAROSTOVÉ A NEZÁVISLÍ","hlasy":5295,"mandaty":5,"kandidatu":14}]},{"kod":"538329","nazev":"Klíčany","okres":"Praha-východ","kraj":"Středočeský kraj","obyvatel":558,"mandatu":7,"okresNuts":"CZ0209","volicu":345,"ucast":36.81,"platneHlasy":464,"strany":[{"nazev":"MICHAL CHUDOBA","hlasy":61,"mandaty":1,"kandidatu":1},{"nazev":"VÁCLAV NOVÁČEK","hlasy":76,"mandaty":1,"kandidatu":1},{"nazev":"IVETA KRUTILKOVÁ","hlasy":66,"mandaty":1,"kandidatu":1},{"nazev":"JANA PRÁŠKOVÁ","hlasy":67,"mandaty":1,"kandidatu":1},{"nazev":"VERONIKA NOVÁČKOVÁ","hlasy":67,"mandaty":1,"kandidatu":1},{"nazev":"PETR HEJSEK","hlasy":48,"mandaty":1,"kandidatu":1},{"nazev":"JAROSLAV PARUS","hlasy":79,"mandaty":1,"kandidatu":1}]},{"kod":"513628","nazev":"Klokočná","okres":"Praha-východ","kraj":"Středočeský kraj","obyvatel":278,"mandatu":7,"okresNuts":"CZ0209","volicu":218,"ucast":50.46,"platneHlasy":589,"strany":[{"nazev":"NEZÁVISLÍ PRO LEPŠÍ KLOKOČNOU 2022","hlasy":589,"mandaty":7,"kandidatu":8}]},{"kod":"531553","nazev":"Konětopy","okres":"Praha-východ","kraj":"Středočeský kraj","obyvatel":315,"mandatu":7,"okresNuts":"CZ0209","volicu":252,"ucast":63.1,"platneHlasy":857,"strany":[{"nazev":"JAROSLAV KOŠ","hlasy":63,"mandaty":0,"kandidatu":1},{"nazev":"JOSEF LITOCHLEB","hlasy":78,"mandaty":0,"kandidatu":1},{"nazev":"PRO KONĚTOPY","hlasy":716,"mandaty":7,"kandidatu":9}]},{"kod":"564761","nazev":"Konojedy","okres":"Praha-východ","kraj":"Středočeský kraj","obyvatel":270,"mandatu":7,"okresNuts":"CZ0209","volicu":210,"ucast":33.81,"platneHlasy":408,"strany":[{"nazev":"DOBROMYSL KONOJEDY","hlasy":408,"mandaty":7,"kandidatu":9}]},{"kod":"533416","nazev":"Kostelec nad Černými lesy","okres":"Praha-východ","kraj":"Středočeský kraj","obyvatel":3773,"mandatu":15,"okresNuts":"CZ0209","volicu":2878,"ucast":43.29,"platneHlasy":16624,"strany":[{"nazev":"Kostelec Sobě - Nezávislí","hlasy":5461,"mandaty":5,"kandidatu":15},{"nazev":"Sdružení nezávislých kandidátů, členů a sympatizantů SDH (Sboru dobrovolných hasičů)","hlasy":1963,"mandaty":2,"kandidatu":15},{"nazev":"STAROSTOVÉ A NEZÁVISLÍ","hlasy":3366,"mandaty":3,"kandidatu":15},{"nazev":"OK 2022 OBČANSKÁ KOALICE","hlasy":4484,"mandaty":4,"kandidatu":15},{"nazev":"KSČM, ČSSD A NESTRANÍCI PRO KOSTELEC A SVATBÍN – SPOLEČNÁ LEVICE PRO UDRŽITELNÝ ŽIVOT VŠECH GENERACÍ…","hlasy":1350,"mandaty":1,"kandidatu":15}]},{"kod":"538370","nazev":"Kostelec u Křížků","okres":"Praha-východ","kraj":"Středočeský kraj","obyvatel":756,"mandatu":7,"okresNuts":"CZ0209","volicu":565,"ucast":61.59,"platneHlasy":2136,"strany":[{"nazev":"Kosteláci","hlasy":815,"mandaty":3,"kandidatu":7},{"nazev":"Nezávislí","hlasy":1321,"mandaty":4,"kandidatu":7}]},{"kod":"536130","nazev":"Kostelní Hlavno","okres":"Praha-východ","kraj":"Středočeský kraj","obyvatel":519,"mandatu":7,"okresNuts":"CZ0209","volicu":363,"ucast":44.9,"platneHlasy":826,"strany":[{"nazev":"Sdružení pro občany Kostelního Hlavna","hlasy":826,"mandaty":7,"kandidatu":7}]},{"kod":"533432","nazev":"Kozojedy","okres":"Praha-východ","kraj":"Středočeský kraj","obyvatel":951,"mandatu":9,"okresNuts":"CZ0209","volicu":706,"ucast":64.59,"platneHlasy":3725,"strany":[{"nazev":"Za klidné Kozojedy","hlasy":2792,"mandaty":7,"kandidatu":9},{"nazev":"Sdružení nezávislých kandidátů pro spokojený život v Kozojedech","hlasy":933,"mandaty":2,"kandidatu":9}]},{"kod":"534960","nazev":"Křenek","okres":"Praha-východ","kraj":"Středočeský kraj","obyvatel":301,"mandatu":7,"okresNuts":"CZ0209","volicu":232,"ucast":75.43,"platneHlasy":812,"strany":[{"nazev":"JAROSLAV ŘÍMAL","hlasy":70,"mandaty":1,"kandidatu":1},{"nazev":"JIŘÍ NOVÁK","hlasy":95,"mandaty":1,"kandidatu":1},{"nazev":"BC. LUCIE PELCOVÁ, DIS.","hlasy":87,"mandaty":1,"kandidatu":1},{"nazev":"JAROSLAV NOVÁK","hlasy":103,"mandaty":1,"kandidatu":1},{"nazev":"LUBOMÍR ČERNÝ","hlasy":55,"mandaty":0,"kandidatu":1},{"nazev":"VLASTIMIL KLÁŠTERKA","hlasy":67,"mandaty":1,"kandidatu":1},{"nazev":"MAREK ČERNÝ","hlasy":56,"mandaty":0,"kandidatu":1},{"nazev":"TOP 09","hlasy":99,"mandaty":1,"kandidatu":1},{"nazev":"ING. TOMÁŠ MACHKA","hlasy":102,"mandaty":1,"kandidatu":1},{"nazev":"MIROSLAV MÁLEK","hlasy":26,"mandaty":0,"kandidatu":1},{"nazev":"MILAN MACHKA","hlasy":52,"mandaty":0,"kandidatu":1}]},{"kod":"564991","nazev":"Křenice","okres":"Praha-východ","kraj":"Středočeský kraj","obyvatel":908,"mandatu":7,"okresNuts":"CZ0209","volicu":618,"ucast":32.36,"platneHlasy":1295,"strany":[{"nazev":"PRO – Pro Rozvoj Obce Křenice","hlasy":1295,"mandaty":7,"kandidatu":8}]},{"kod":"538418","nazev":"Křížkový Újezdec","okres":"Praha-východ","kraj":"Středočeský kraj","obyvatel":285,"mandatu":7,"okresNuts":"CZ0209","volicu":217,"ucast":77.88,"platneHlasy":1159,"strany":[{"nazev":"NEZÁVISLÍ OBČANÉ","hlasy":32,"mandaty":0,"kandidatu":3},{"nazev":"Sdružení nezávislých kandidátů pro Křížkový Újezdec","hlasy":141,"mandaty":1,"kandidatu":7},{"nazev":"„Za Nás“","hlasy":128,"mandaty":0,"kandidatu":7},{"nazev":"Sousedé pro obec","hlasy":592,"mandaty":4,"kandidatu":7},{"nazev":"PRO OBČANY","hlasy":266,"mandaty":2,"kandidatu":7}]},{"kod":"538426","nazev":"Kunice","okres":"Praha-východ","kraj":"Středočeský kraj","obyvatel":1734,"mandatu":11,"okresNuts":"CZ0209","volicu":1241,"ucast":30.46,"platneHlasy":2827,"strany":[{"nazev":"Sdružení nezávislých kandidátů Kunice","hlasy":2827,"mandaty":11,"kandidatu":11}]},{"kod":"564982","nazev":"Květnice","okres":"Praha-východ","kraj":"Středočeský kraj","obyvatel":1923,"mandatu":7,"okresNuts":"CZ0209","volicu":1237,"ucast":64.11,"platneHlasy":5437,"strany":[{"nazev":"Květnice vzkvétající","hlasy":1621,"mandaty":2,"kandidatu":9},{"nazev":"Jedna Květnice, jedno místo pro život","hlasy":3040,"mandaty":4,"kandidatu":9},{"nazev":"Občanská demokratická strana","hlasy":776,"mandaty":1,"kandidatu":7}]},{"kod":"538914","nazev":"Lázně Toušeň","okres":"Praha-východ","kraj":"Středočeský kraj","obyvatel":1439,"mandatu":15,"okresNuts":"CZ0209","volicu":1038,"ucast":52.79,"platneHlasy":7107,"strany":[{"nazev":"Občanská demokratická strana","hlasy":373,"mandaty":0,"kandidatu":8},{"nazev":"STAROSTOVÉ A NEZÁVISLÍ","hlasy":1974,"mandaty":4,"kandidatu":15},{"nazev":"Nezávislí kandidáti za Lázně Toušeň","hlasy":2333,"mandaty":5,"kandidatu":15},{"nazev":"Dobrá volba pro Toušeň","hlasy":2427,"mandaty":6,"kandidatu":15}]},{"kod":"534986","nazev":"Lhota","okres":"Praha-východ","kraj":"Středočeský kraj","obyvatel":479,"mandatu":7,"okresNuts":"CZ0209","volicu":386,"ucast":56.48,"platneHlasy":1033,"strany":[{"nazev":"LHOTA 2022-2026","hlasy":1033,"mandaty":7,"kandidatu":9}]},{"kod":"538442","nazev":"Líbeznice","okres":"Praha-východ","kraj":"Středočeský kraj","obyvatel":3030,"mandatu":15,"okresNuts":"CZ0209","volicu":1932,"ucast":51.14,"platneHlasy":13006,"strany":[{"nazev":"Sdružení nezávislých kandidátů PRO LÍBEZNICE","hlasy":3943,"mandaty":4,"kandidatu":15},{"nazev":"Občanská demokratická strana","hlasy":9063,"mandaty":11,"kandidatu":15}]},{"kod":"538451","nazev":"Louňovice","okres":"Praha-východ","kraj":"Středočeský kraj","obyvatel":1169,"mandatu":9,"okresNuts":"CZ0209","volicu":868,"ucast":56.34,"platneHlasy":3879,"strany":[{"nazev":"SDRUŽENÍ NEZÁVISLÝCH I.","hlasy":1834,"mandaty":4,"kandidatu":9},{"nazev":"SDRUŽENÍ NEZÁVISLÝCH II.","hlasy":2045,"mandaty":5,"kandidatu":9}]},{"kod":"538469","nazev":"Máslovice","okres":"Praha-východ","kraj":"Středočeský kraj","obyvatel":383,"mandatu":7,"okresNuts":"CZ0209","volicu":314,"ucast":44.59,"platneHlasy":618,"strany":[{"nazev":"Sdružení nezávislých kandidátů obce Máslovice","hlasy":618,"mandaty":7,"kandidatu":7}]},{"kod":"538477","nazev":"Měšice","okres":"Praha-východ","kraj":"Středočeský kraj","obyvatel":2037,"mandatu":15,"okresNuts":"CZ0209","volicu":1438,"ucast":57.72,"platneHlasy":11356,"strany":[{"nazev":"S námi za lepší Měšice","hlasy":3309,"mandaty":4,"kandidatu":15},{"nazev":"MĚŠICKÝ KRUH","hlasy":8047,"mandaty":11,"kandidatu":15}]},{"kod":"538485","nazev":"Mirošovice","okres":"Praha-východ","kraj":"Středočeský kraj","obyvatel":1455,"mandatu":9,"okresNuts":"CZ0209","volicu":967,"ucast":26.58,"platneHlasy":1445,"strany":[{"nazev":"STAROSTOVÉ A NEZÁVISLÍ","hlasy":1445,"mandaty":9,"kandidatu":9}]},{"kod":"538493","nazev":"Mnichovice","okres":"Praha-východ","kraj":"Středočeský kraj","obyvatel":3964,"mandatu":11,"okresNuts":"CZ0209","volicu":2822,"ucast":41.71,"platneHlasy":11326,"strany":[{"nazev":"MNICHOVICE – MĚSTO NA VAŠÍ STRANĚ","hlasy":9102,"mandaty":9,"kandidatu":11},{"nazev":"KDU-ČSL","hlasy":2224,"mandaty":2,"kandidatu":11}]},{"kod":"598267","nazev":"Modletice","okres":"Praha-východ","kraj":"Středočeský kraj","obyvatel":528,"mandatu":7,"okresNuts":"CZ0209","volicu":337,"ucast":25.22,"platneHlasy":450,"strany":[{"nazev":"ZA MODLETICE","hlasy":450,"mandaty":7,"kandidatu":7}]},{"kod":"538507","nazev":"Mochov","okres":"Praha-východ","kraj":"Středočeský kraj","obyvatel":1346,"mandatu":11,"okresNuts":"CZ0209","volicu":790,"ucast":55.32,"platneHlasy":4584,"strany":[{"nazev":"Kandidáti pro Mochov - Sdružení nezávislých kandidátů","hlasy":1397,"mandaty":3,"kandidatu":11},{"nazev":"Náš Mochov","hlasy":3187,"mandaty":8,"kandidatu":11}]},{"kod":"538515","nazev":"Mratín","okres":"Praha-východ","kraj":"Středočeský kraj","obyvatel":1395,"mandatu":7,"okresNuts":"CZ0209","volicu":899,"ucast":39.04,"platneHlasy":1494,"strany":[{"nazev":"MRATÍN PRO OBČANY","hlasy":1494,"mandaty":7,"kandidatu":7}]},{"kod":"538523","nazev":"Mukařov","okres":"Praha-východ","kraj":"Středočeský kraj","obyvatel":2772,"mandatu":15,"okresNuts":"CZ0209","volicu":1991,"ucast":57.21,"platneHlasy":15774,"strany":[{"nazev":"SPOLEČNĚ s TOP 09 pro lepší MUKAŘOVSKO","hlasy":3605,"mandaty":4,"kandidatu":15},{"nazev":"Sdružení nezávislých kandidátů s podporou Svobodných","hlasy":1782,"mandaty":1,"kandidatu":15},{"nazev":"ZVON","hlasy":3313,"mandaty":3,"kandidatu":15},{"nazev":"Sdružení kandidátů Mukařov, Srbín, Žernovka","hlasy":7074,"mandaty":7,"kandidatu":15}]},{"kod":"538540","nazev":"Nehvizdy","okres":"Praha-východ","kraj":"Středočeský kraj","obyvatel":3833,"mandatu":15,"okresNuts":"CZ0209","volicu":2289,"ucast":38.75,"platneHlasy":11493,"strany":[{"nazev":"STAROSTOVÉ A NEZÁVISLÍ","hlasy":8247,"mandaty":11,"kandidatu":15},{"nazev":"TOP 09 a Nezávislí pro Nehvizdy","hlasy":3246,"mandaty":4,"kandidatu":15}]},{"kod":"538558","nazev":"Nová Ves","okres":"Praha-východ","kraj":"Středočeský kraj","obyvatel":1417,"mandatu":7,"okresNuts":"CZ0209","volicu":906,"ucast":40.29,"platneHlasy":1838,"strany":[{"nazev":"Sdružení nezávislých kandidátů NOVÁ VES","hlasy":1838,"mandaty":7,"kandidatu":8}]},{"kod":"538566","nazev":"Nový Vestec","okres":"Praha-východ","kraj":"Středočeský kraj","obyvatel":490,"mandatu":7,"okresNuts":"CZ0209","volicu":382,"ucast":45.03,"platneHlasy":778,"strany":[{"nazev":"Sdružení nezávislých kandidátů obce Nový Vestec","hlasy":778,"mandaty":7,"kandidatu":7}]},{"kod":"533548","nazev":"Nučice","okres":"Praha-východ","kraj":"Středočeský kraj","obyvatel":366,"mandatu":7,"okresNuts":"CZ0209","volicu":293,"ucast":58.36,"platneHlasy":1143,"strany":[{"nazev":"Pro naši obec","hlasy":874,"mandaty":6,"kandidatu":9},{"nazev":"Změna","hlasy":269,"mandaty":1,"kandidatu":7}]},{"kod":"564907","nazev":"Nupaky","okres":"Praha-východ","kraj":"Středočeský kraj","obyvatel":1876,"mandatu":9,"okresNuts":"CZ0209","volicu":1024,"ucast":49.41,"platneHlasy":4202,"strany":[{"nazev":"Budoucnost pro Nupaky","hlasy":308,"mandaty":0,"kandidatu":7},{"nazev":"SDRUŽENÍ NEZÁVISLÝCH KANDIDÁTŮ NUPAKY ROZUMEM A CITEM","hlasy":1746,"mandaty":4,"kandidatu":9},{"nazev":"Nupaky sobě s podporou ODS","hlasy":1032,"mandaty":2,"kandidatu":9},{"nazev":"PRO NUPAKY","hlasy":1116,"mandaty":3,"kandidatu":9}]},{"kod":"538574","nazev":"Odolena Voda","okres":"Praha-východ","kraj":"Středočeský kraj","obyvatel":6163,"mandatu":15,"okresNuts":"CZ0209","volicu":4463,"ucast":46.58,"platneHlasy":27504,"strany":[{"nazev":"Česká strana sociálně demokratická a nezávislí kandidáti","hlasy":3515,"mandaty":2,"kandidatu":15},{"nazev":"Odolní – Sdružení pro Odolenu Vodu, Dolínek a Čenkov","hlasy":9294,"mandaty":5,"kandidatu":15},{"nazev":"VODOLÁCI","hlasy":5688,"mandaty":3,"kandidatu":15},{"nazev":"SPOLEČNĚ","hlasy":4088,"mandaty":2,"kandidatu":15},{"nazev":"Občanská demokratická strana a nezávislí kandidáti","hlasy":4919,"mandaty":3,"kandidatu":15}]},{"kod":"533564","nazev":"Oleška","okres":"Praha-východ","kraj":"Středočeský kraj","obyvatel":964,"mandatu":15,"okresNuts":"CZ0209","volicu":739,"ucast":61.3,"platneHlasy":5554,"strany":[{"nazev":"Pro naše vesnice","hlasy":4055,"mandaty":11,"kandidatu":15},{"nazev":"Bc. Karel Hetzendorf","hlasy":75,"mandaty":0,"kandidatu":1},{"nazev":"NAŠE VESNICE","hlasy":1424,"mandaty":4,"kandidatu":15}]},{"kod":"538582","nazev":"Ondřejov","okres":"Praha-východ","kraj":"Středočeský kraj","obyvatel":1804,"mandatu":15,"okresNuts":"CZ0209","volicu":1279,"ucast":31.2,"platneHlasy":3912,"strany":[{"nazev":"Správná volba pro Ondřejov, Třemblaty a Turkovice","hlasy":3912,"mandaty":15,"kandidatu":15}]},{"kod":"571679","nazev":"Oplany","okres":"Praha-východ","kraj":"Středočeský kraj","obyvatel":105,"mandatu":7,"okresNuts":"CZ0209","volicu":84,"ucast":63.1,"platneHlasy":307,"strany":[{"nazev":"OPLANY SOBĚ","hlasy":307,"mandaty":7,"kandidatu":9}]},{"kod":"538604","nazev":"Panenské Břežany","okres":"Praha-východ","kraj":"Středočeský kraj","obyvatel":621,"mandatu":7,"okresNuts":"CZ0209","volicu":460,"ucast":46.52,"platneHlasy":1199,"strany":[{"nazev":"BŘEŽAŇÁCI 2018 – Společně pro Břežany","hlasy":1199,"mandaty":7,"kandidatu":7}]},{"kod":"529656","nazev":"Pětihosty","okres":"Praha-východ","kraj":"Středočeský kraj","obyvatel":246,"mandatu":7,"okresNuts":"CZ0209","volicu":174,"ucast":46.55,"platneHlasy":445,"strany":[{"nazev":"ZACHOVÁNÍ VENKOVA","hlasy":445,"mandaty":7,"kandidatu":9}]},{"kod":"538612","nazev":"Petříkov","okres":"Praha-východ","kraj":"Středočeský kraj","obyvatel":604,"mandatu":7,"okresNuts":"CZ0209","volicu":440,"ucast":41.36,"platneHlasy":858,"strany":[{"nazev":"Sdružení pro obec 22","hlasy":858,"mandaty":7,"kandidatu":7}]},{"kod":"538621","nazev":"Podolanka","okres":"Praha-východ","kraj":"Středočeský kraj","obyvatel":586,"mandatu":7,"okresNuts":"CZ0209","volicu":468,"ucast":63.03,"platneHlasy":1913,"strany":[{"nazev":"Sdružení nezávislých kandidátů Podolanka","hlasy":1166,"mandaty":4,"kandidatu":7},{"nazev":"SPOLEČNĚ PRO ZMĚNU - SNK","hlasy":747,"mandaty":3,"kandidatu":8}]},{"kod":"538639","nazev":"Polerady","okres":"Praha-východ","kraj":"Středočeský kraj","obyvatel":483,"mandatu":7,"okresNuts":"CZ0209","volicu":336,"ucast":59.52,"platneHlasy":1252,"strany":[{"nazev":"ZA NAŠE POLERADY","hlasy":1095,"mandaty":6,"kandidatu":8},{"nazev":"Nové Polerady","hlasy":157,"mandaty":1,"kandidatu":7}]},{"kod":"599221","nazev":"Popovičky","okres":"Praha-východ","kraj":"Středočeský kraj","obyvatel":433,"mandatu":7,"okresNuts":"CZ0209","volicu":310,"ucast":74.19,"platneHlasy":1563,"strany":[{"nazev":"SPOLEČNĚ S VÁMI","hlasy":1119,"mandaty":5,"kandidatu":9},{"nazev":"Venkov pro lidi","hlasy":444,"mandaty":2,"kandidatu":7}]},{"kod":"564788","nazev":"Prusice","okres":"Praha-východ","kraj":"Středočeský kraj","obyvatel":91,"mandatu":7,"okresNuts":"CZ0209","volicu":66,"ucast":63.64,"platneHlasy":220,"strany":[{"nazev":"Dalibor Plaček","hlasy":13,"mandaty":0,"kandidatu":1},{"nazev":"Volby 2022","hlasy":207,"mandaty":7,"kandidatu":9}]},{"kod":"538655","nazev":"Předboj","okres":"Praha-východ","kraj":"Středočeský kraj","obyvatel":1226,"mandatu":7,"okresNuts":"CZ0209","volicu":807,"ucast":61.71,"platneHlasy":3330,"strany":[{"nazev":"SDRUŽENÍ NEZÁVISLÝCH KANDIDÁTŮ","hlasy":1274,"mandaty":3,"kandidatu":8},{"nazev":"SPOLU PRO PŘEDBOJ","hlasy":2056,"mandaty":4,"kandidatu":9}]},{"kod":"538671","nazev":"Přezletice","okres":"Praha-východ","kraj":"Středočeský kraj","obyvatel":2024,"mandatu":7,"okresNuts":"CZ0209","volicu":1376,"ucast":37.28,"platneHlasy":2231,"strany":[{"nazev":"Přezleťáci","hlasy":2231,"mandaty":7,"kandidatu":9}]},{"kod":"538698","nazev":"Radějovice","okres":"Praha-východ","kraj":"Středočeský kraj","obyvatel":500,"mandatu":9,"okresNuts":"CZ0209","volicu":387,"ucast":72.61,"platneHlasy":2457,"strany":[{"nazev":"Občané pro obec","hlasy":709,"mandaty":2,"kandidatu":9},{"nazev":"Obec pro občany","hlasy":1748,"mandaty":7,"kandidatu":9}]},{"kod":"538701","nazev":"Radonice","okres":"Praha-východ","kraj":"Středočeský kraj","obyvatel":1074,"mandatu":15,"okresNuts":"CZ0209","volicu":749,"ucast":36.18,"platneHlasy":2370,"strany":[{"nazev":"Společně pro obec 2022","hlasy":2370,"mandaty":15,"kandidatu":15}]},{"kod":"538728","nazev":"Říčany","okres":"Praha-východ","kraj":"Středočeský kraj","obyvatel":16182,"mandatu":21,"okresNuts":"CZ0209","volicu":11705,"ucast":51.09,"platneHlasy":118256,"strany":[{"nazev":"Klidné město","hlasy":53512,"mandaty":10,"kandidatu":21},{"nazev":"ZMĚNA PRO ŘÍČANY – STAN","hlasy":34648,"mandaty":6,"kandidatu":21},{"nazev":"Unie pro sport a zdraví Říčany","hlasy":12846,"mandaty":2,"kandidatu":21},{"nazev":"SPOLU","hlasy":17250,"mandaty":3,"kandidatu":21}]},{"kod":"598283","nazev":"Sedlec","okres":"Praha-východ","kraj":"Středočeský kraj","obyvatel":429,"mandatu":7,"okresNuts":"CZ0209","volicu":286,"ucast":71.68,"platneHlasy":1307,"strany":[{"nazev":"Sedlec – místo pro život","hlasy":1033,"mandaty":6,"kandidatu":8},{"nazev":"Sdružení nezávislých kandidátů Sedlec pro lidi","hlasy":274,"mandaty":1,"kandidatu":6}]},{"kod":"538752","nazev":"Senohraby","okres":"Praha-východ","kraj":"Středočeský kraj","obyvatel":1244,"mandatu":9,"okresNuts":"CZ0209","volicu":964,"ucast":65.46,"platneHlasy":5514,"strany":[{"nazev":"Hasiči Senohraby","hlasy":957,"mandaty":1,"kandidatu":9},{"nazev":"Senohraby DOHROMADY","hlasy":1666,"mandaty":3,"kandidatu":9},{"nazev":"TJ Sokol Senohraby","hlasy":1568,"mandaty":3,"kandidatu":9},{"nazev":"Sdružení občanů pro Senohraby","hlasy":1157,"mandaty":2,"kandidatu":9},{"nazev":"SPRÁVNÁ VOLBA","hlasy":166,"mandaty":0,"kandidatu":9}]},{"kod":"538761","nazev":"Sibřina","okres":"Praha-východ","kraj":"Středočeský kraj","obyvatel":942,"mandatu":9,"okresNuts":"CZ0209","volicu":672,"ucast":50.3,"platneHlasy":2627,"strany":[{"nazev":"NAŠE OBEC","hlasy":1198,"mandaty":4,"kandidatu":9},{"nazev":"Sdružení pro Sibřinu a Stupice","hlasy":1429,"mandaty":5,"kandidatu":9}]},{"kod":"538779","nazev":"Sluhy","okres":"Praha-východ","kraj":"Středočeský kraj","obyvatel":726,"mandatu":7,"okresNuts":"CZ0209","volicu":569,"ucast":56.59,"platneHlasy":2037,"strany":[{"nazev":"NOVÉ SLUHY","hlasy":1106,"mandaty":4,"kandidatu":8},{"nazev":"Za Sluhy","hlasy":349,"mandaty":1,"kandidatu":5},{"nazev":"Sdružení nezávislých kandidátů: BUDOUCNOST PRO SLUHY","hlasy":0,"mandaty":0,"kandidatu":0},{"nazev":"Sluhy 1088","hlasy":582,"mandaty":2,"kandidatu":7}]},{"kod":"538787","nazev":"Sluštice","okres":"Praha-východ","kraj":"Středočeský kraj","obyvatel":682,"mandatu":9,"okresNuts":"CZ0209","volicu":527,"ucast":62.05,"platneHlasy":2682,"strany":[{"nazev":"Sdružení zastupitelů obce Sluštice","hlasy":2370,"mandaty":8,"kandidatu":9},{"nazev":"ZA NORMÁLNÍ SLUŠTICE","hlasy":312,"mandaty":1,"kandidatu":7}]},{"kod":"538809","nazev":"Strančice","okres":"Praha-východ","kraj":"Středočeský kraj","obyvatel":2594,"mandatu":15,"okresNuts":"CZ0209","volicu":1816,"ucast":58.59,"platneHlasy":15190,"strany":[{"nazev":"Společně pro Strančice, Kašovice, Otice, Předboř, Sklenku, Svojšovice a Všechromy","hlasy":10942,"mandaty":11,"kandidatu":15},{"nazev":"Sdružení nezávislých kandidátů pro Strančice a přidružené obce","hlasy":4248,"mandaty":4,"kandidatu":15}]},{"kod":"538825","nazev":"Struhařov","okres":"Praha-východ","kraj":"Středočeský kraj","obyvatel":944,"mandatu":9,"okresNuts":"CZ0209","volicu":721,"ucast":57.7,"platneHlasy":3491,"strany":[{"nazev":"SOKOL","hlasy":1569,"mandaty":4,"kandidatu":9},{"nazev":"Struhařov žije 2022","hlasy":1922,"mandaty":5,"kandidatu":9}]},{"kod":"533718","nazev":"Stříbrná Skalice","okres":"Praha-východ","kraj":"Středočeský kraj","obyvatel":1494,"mandatu":13,"okresNuts":"CZ0209","volicu":1192,"ucast":55.79,"platneHlasy":7595,"strany":[{"nazev":"MÍSTNÍ","hlasy":4295,"mandaty":7,"kandidatu":13},{"nazev":"PATRIOTI SKALICKA","hlasy":3300,"mandaty":6,"kandidatu":13}]},{"kod":"571954","nazev":"Sudovo Hlavno","okres":"Praha-východ","kraj":"Středočeský kraj","obyvatel":517,"mandatu":7,"okresNuts":"CZ0209","volicu":397,"ucast":72.54,"platneHlasy":1920,"strany":[{"nazev":"Za Sudovo Hlavno","hlasy":1088,"mandaty":4,"kandidatu":9},{"nazev":"Naše Hlavno 1","hlasy":525,"mandaty":2,"kandidatu":7},{"nazev":"Naše Hlavno 2","hlasy":307,"mandaty":1,"kandidatu":6}]},{"kod":"538833","nazev":"Sulice","okres":"Praha-východ","kraj":"Středočeský kraj","obyvatel":2280,"mandatu":13,"okresNuts":"CZ0209","volicu":1621,"ucast":33.44,"platneHlasy":5002,"strany":[{"nazev":"Sdružení nezávislých kandidátů - Prosperující obec 2026","hlasy":5002,"mandaty":13,"kandidatu":13}]},{"kod":"598305","nazev":"Svémyslice","okres":"Praha-východ","kraj":"Středočeský kraj","obyvatel":522,"mandatu":7,"okresNuts":"CZ0209","volicu":336,"ucast":49.4,"platneHlasy":993,"strany":[{"nazev":"STAROSTOVÉ A NEZÁVISLÍ","hlasy":993,"mandaty":7,"kandidatu":9}]},{"kod":"538841","nazev":"Světice","okres":"Praha-východ","kraj":"Středočeský kraj","obyvatel":1302,"mandatu":9,"okresNuts":"CZ0209","volicu":949,"ucast":57.32,"platneHlasy":4671,"strany":[{"nazev":"PATRIOTI - Světice","hlasy":1157,"mandaty":2,"kandidatu":9},{"nazev":"Nezávislí pro Světice","hlasy":1440,"mandaty":3,"kandidatu":9},{"nazev":"STAROSTOVÉ A NEZÁVISLÍ","hlasy":2074,"mandaty":4,"kandidatu":9}]},{"kod":"538850","nazev":"Svojetice","okres":"Praha-východ","kraj":"Středočeský kraj","obyvatel":1219,"mandatu":9,"okresNuts":"CZ0209","volicu":894,"ucast":61.86,"platneHlasy":4743,"strany":[{"nazev":"SVOJETICE 2018","hlasy":2712,"mandaty":5,"kandidatu":9},{"nazev":"Sdružení nezávislých kandidátů PRO SVOJETICE","hlasy":2031,"mandaty":4,"kandidatu":9}]},{"kod":"538876","nazev":"Šestajovice","okres":"Praha-východ","kraj":"Středočeský kraj","obyvatel":3957,"mandatu":11,"okresNuts":"CZ0209","volicu":2703,"ucast":28.23,"platneHlasy":6135,"strany":[{"nazev":"SNK Šestajovice","hlasy":6135,"mandaty":11,"kandidatu":11}]},{"kod":"538884","nazev":"Škvorec","okres":"Praha-východ","kraj":"Středočeský kraj","obyvatel":2036,"mandatu":11,"okresNuts":"CZ0209","volicu":1457,"ucast":63.62,"platneHlasy":9891,"strany":[{"nazev":"Sdružení nezávislých pro Škvorec a Třebohostice","hlasy":1439,"mandaty":1,"kandidatu":11},{"nazev":"SOUSEDÉ","hlasy":6250,"mandaty":8,"kandidatu":11},{"nazev":"Občanská demokratická strana a nezávislí","hlasy":2202,"mandaty":2,"kandidatu":11}]},{"kod":"571644","nazev":"Štíhlice","okres":"Praha-východ","kraj":"Středočeský kraj","obyvatel":212,"mandatu":7,"okresNuts":"CZ0209","volicu":161,"ucast":58.39,"platneHlasy":464,"strany":[{"nazev":"SDRUŽENÍ NEZÁVISLÝCH KANDIDÁTŮ","hlasy":464,"mandaty":7,"kandidatu":8}]},{"kod":"538892","nazev":"Tehov","okres":"Praha-východ","kraj":"Středočeský kraj","obyvatel":1055,"mandatu":9,"okresNuts":"CZ0209","volicu":764,"ucast":68.19,"platneHlasy":4505,"strany":[{"nazev":"Nová volba pro Tehov","hlasy":1582,"mandaty":3,"kandidatu":9},{"nazev":"Tehov 2022","hlasy":2923,"mandaty":6,"kandidatu":9}]},{"kod":"599719","nazev":"Tehovec","okres":"Praha-východ","kraj":"Středočeský kraj","obyvatel":640,"mandatu":7,"okresNuts":"CZ0209","volicu":486,"ucast":41.15,"platneHlasy":1059,"strany":[{"nazev":"Nezávislí kandidáti Tehovec I.","hlasy":1059,"mandaty":7,"kandidatu":9}]},{"kod":"538957","nazev":"Úvaly","okres":"Praha-východ","kraj":"Středočeský kraj","obyvatel":7035,"mandatu":15,"okresNuts":"CZ0209","volicu":5147,"ucast":47.72,"platneHlasy":33975,"strany":[{"nazev":"TOP 09","hlasy":4159,"mandaty":2,"kandidatu":15},{"nazev":"Otevřené Úvaly","hlasy":10027,"mandaty":4,"kandidatu":15},{"nazev":"Česká strana sociálně demokratická","hlasy":2253,"mandaty":1,"kandidatu":15},{"nazev":"Občanská demokratická strana","hlasy":6628,"mandaty":3,"kandidatu":15},{"nazev":"PRO Úvaly","hlasy":10908,"mandaty":5,"kandidatu":15}]},{"kod":"538965","nazev":"Veleň","okres":"Praha-východ","kraj":"Středočeský kraj","obyvatel":1757,"mandatu":9,"okresNuts":"CZ0209","volicu":1185,"ucast":42.62,"platneHlasy":3218,"strany":[{"nazev":"Sdružení nezávislých kandidátů I","hlasy":3218,"mandaty":9,"kandidatu":9}]},{"kod":"538973","nazev":"Veliká Ves","okres":"Praha-východ","kraj":"Středočeský kraj","obyvatel":388,"mandatu":7,"okresNuts":"CZ0209","volicu":290,"ucast":44.48,"platneHlasy":623,"strany":[{"nazev":"Nezávislí kandidáti","hlasy":623,"mandaty":7,"kandidatu":9}]},{"kod":"538981","nazev":"Velké Popovice","okres":"Praha-východ","kraj":"Středočeský kraj","obyvatel":3110,"mandatu":15,"okresNuts":"CZ0209","volicu":2128,"ucast":55.08,"platneHlasy":16495,"strany":[{"nazev":"Lidé VelkoPopovicka","hlasy":5077,"mandaty":5,"kandidatu":15},{"nazev":"NEZÁVISLÍ S PODPOROU ODS","hlasy":6381,"mandaty":6,"kandidatu":15},{"nazev":"OTEVŘENI KE ZMĚNÁM","hlasy":5037,"mandaty":4,"kandidatu":15}]},{"kod":"538990","nazev":"Větrušice","okres":"Praha-východ","kraj":"Středočeský kraj","obyvatel":662,"mandatu":7,"okresNuts":"CZ0209","volicu":479,"ucast":50.52,"platneHlasy":1271,"strany":[{"nazev":"Pro Větrušice","hlasy":1271,"mandaty":7,"kandidatu":9}]},{"kod":"533874","nazev":"Vlkančice","okres":"Praha-východ","kraj":"Středočeský kraj","obyvatel":210,"mandatu":9,"okresNuts":"CZ0209","volicu":168,"ucast":44.64,"platneHlasy":484,"strany":[{"nazev":"Vlkančice 2022","hlasy":484,"mandaty":9,"kandidatu":9}]},{"kod":"539015","nazev":"Vodochody","okres":"Praha-východ","kraj":"Středočeský kraj","obyvatel":724,"mandatu":9,"okresNuts":"CZ0209","volicu":491,"ucast":43.18,"platneHlasy":1255,"strany":[{"nazev":"PRO LEPŠÍ VODOCHODY A HOŠTICE","hlasy":1255,"mandaty":9,"kandidatu":9}]},{"kod":"539031","nazev":"Všestary","okres":"Praha-východ","kraj":"Středočeský kraj","obyvatel":952,"mandatu":9,"okresNuts":"CZ0209","volicu":690,"ucast":62.32,"platneHlasy":3580,"strany":[{"nazev":"Naše Všestary","hlasy":1680,"mandaty":4,"kandidatu":9},{"nazev":"Volba pro Všestary, Menčice a Vávrov","hlasy":1900,"mandaty":5,"kandidatu":9}]},{"kod":"539040","nazev":"Vyšehořovice","okres":"Praha-východ","kraj":"Středočeský kraj","obyvatel":661,"mandatu":9,"okresNuts":"CZ0209","volicu":493,"ucast":41.99,"platneHlasy":1097,"strany":[{"nazev":"Sdružení nezávislých kandidátů za spokojený život v obci Vyšehořovice a Kozovazy","hlasy":1097,"mandaty":9,"kandidatu":9}]},{"kod":"564796","nazev":"Výžerky","okres":"Praha-východ","kraj":"Středočeský kraj","obyvatel":175,"mandatu":7,"okresNuts":"CZ0209","volicu":128,"ucast":64.06,"platneHlasy":463,"strany":[{"nazev":"VÝŽERKY 2022","hlasy":463,"mandaty":7,"kandidatu":9}]},{"kod":"533904","nazev":"Vyžlovka","okres":"Praha-východ","kraj":"Středočeský kraj","obyvatel":730,"mandatu":9,"okresNuts":"CZ0209","volicu":552,"ucast":40.76,"platneHlasy":1372,"strany":[{"nazev":"Společně pro Vyžlovku","hlasy":1372,"mandaty":9,"kandidatu":9}]},{"kod":"505781","nazev":"Zápy","okres":"Praha-východ","kraj":"Středočeský kraj","obyvatel":876,"mandatu":7,"okresNuts":"CZ0209","volicu":620,"ucast":48.06,"platneHlasy":1732,"strany":[{"nazev":"Sdružení pro klidné Zápy","hlasy":1732,"mandaty":7,"kandidatu":9}]},{"kod":"535362","nazev":"Záryby","okres":"Praha-východ","kraj":"Středočeský kraj","obyvatel":1046,"mandatu":7,"okresNuts":"CZ0209","volicu":790,"ucast":63.54,"platneHlasy":3199,"strany":[{"nazev":"ZA TRADICE A NOVÉ VIZE NAŠÍ OBCE","hlasy":645,"mandaty":1,"kandidatu":9},{"nazev":"Pro budoucnost obce","hlasy":602,"mandaty":1,"kandidatu":9},{"nazev":"Nový směr - nezávislí kandidáti Záryb - Martinova s podporou ODS","hlasy":264,"mandaty":0,"kandidatu":7},{"nazev":"NAŠE OBEC – NÁŠ DOMOV","hlasy":1688,"mandaty":5,"kandidatu":9}]},{"kod":"539058","nazev":"Zdiby","okres":"Praha-východ","kraj":"Středočeský kraj","obyvatel":3766,"mandatu":15,"okresNuts":"CZ0209","volicu":2519,"ucast":56.33,"platneHlasy":20201,"strany":[{"nazev":"OBČANSKÁ INICIATIVA ZDIBY","hlasy":9224,"mandaty":7,"kandidatu":15},{"nazev":"MY ŽIJEME PRO ZDIBY","hlasy":2333,"mandaty":2,"kandidatu":15},{"nazev":"Sdružení fotbal – Zdiby, Veltěž, Přemyšlení","hlasy":4976,"mandaty":4,"kandidatu":15},{"nazev":"OBEC PRO VŠECHNY GENERACE","hlasy":1813,"mandaty":1,"kandidatu":15},{"nazev":"SPOLEČNĚ PRO ZDIBY s ODS","hlasy":1855,"mandaty":1,"kandidatu":15}]},{"kod":"539066","nazev":"Zeleneč","okres":"Praha-východ","kraj":"Středočeský kraj","obyvatel":3133,"mandatu":11,"okresNuts":"CZ0209","volicu":2184,"ucast":61.49,"platneHlasy":13759,"strany":[{"nazev":"Sousedé pro Zeleneč","hlasy":8167,"mandaty":7,"kandidatu":11},{"nazev":"Zelenečské sdružení nezávislých kandidátů","hlasy":5273,"mandaty":4,"kandidatu":11},{"nazev":"Mgr. ONDŘEJ KOPA","hlasy":319,"mandaty":0,"kandidatu":1}]},{"kod":"513644","nazev":"Zlatá","okres":"Praha-východ","kraj":"Středočeský kraj","obyvatel":390,"mandatu":7,"okresNuts":"CZ0209","volicu":262,"ucast":48.85,"platneHlasy":634,"strany":[{"nazev":"Společně pro Zlatou","hlasy":590,"mandaty":7,"kandidatu":9},{"nazev":"Změna pro Zlatou, nezávislý kandidát na starostu obce","hlasy":44,"mandaty":0,"kandidatu":1}]},{"kod":"539082","nazev":"Zlonín","okres":"Praha-východ","kraj":"Středočeský kraj","obyvatel":1091,"mandatu":7,"okresNuts":"CZ0209","volicu":661,"ucast":59.91,"platneHlasy":2104,"strany":[{"nazev":"Jsme tady PRO Zlonín","hlasy":1913,"mandaty":7,"kandidatu":9},{"nazev":"Ing. Marek Pátek – nezávislý kandidát","hlasy":191,"mandaty":0,"kandidatu":1}]},{"kod":"539091","nazev":"Zvánovice","okres":"Praha-východ","kraj":"Středočeský kraj","obyvatel":579,"mandatu":11,"okresNuts":"CZ0209","volicu":450,"ucast":39.56,"platneHlasy":1118,"strany":[{"nazev":"PRO ZVÁNOVICE","hlasy":1118,"mandaty":11,"kandidatu":11}]}]