[{"kod":"584304","nazev":"Bavory","okres":"Břeclav","kraj":"Jihomoravský kraj","obyvatel":392,"mandatu":7,"okresNuts":"CZ0644","volicu":332,"ucast":59.64,"platneHlasy":1247,"strany":[{"nazev":"SDRUŽENÍ NEZÁVISLÝCH KANDIDÁTŮ BAVORY 2.","hlasy":488,"mandaty":3,"kandidatu":7},{"nazev":"KDU-ČSL","hlasy":168,"mandaty":1,"kandidatu":6},{"nazev":"Linda Holcová","hlasy":83,"mandaty":0,"kandidatu":1},{"nazev":"SDRUŽENÍ NEZÁVISLÝCH KANDIDÁTŮ BAVORY 1.","hlasy":508,"mandaty":3,"kandidatu":7}]},{"kod":"584321","nazev":"Boleradice","okres":"Břeclav","kraj":"Jihomoravský kraj","obyvatel":903,"mandatu":15,"okresNuts":"CZ0644","volicu":748,"ucast":59.22,"platneHlasy":6219,"strany":[{"nazev":"NESTRANÍCI PRO BOLERADICE","hlasy":2923,"mandaty":7,"kandidatu":15},{"nazev":"Nezávislí","hlasy":1835,"mandaty":5,"kandidatu":15},{"nazev":"KDU-ČSL","hlasy":1461,"mandaty":3,"kandidatu":15}]},{"kod":"584339","nazev":"Borkovany","okres":"Břeclav","kraj":"Jihomoravský kraj","obyvatel":850,"mandatu":9,"okresNuts":"CZ0644","volicu":662,"ucast":58.46,"platneHlasy":2702,"strany":[{"nazev":"KDU-ČSL","hlasy":814,"mandaty":3,"kandidatu":9},{"nazev":"STAROSTOVÉ A NEZÁVISLÍ","hlasy":1888,"mandaty":6,"kandidatu":9}]},{"kod":"584347","nazev":"Bořetice","okres":"Břeclav","kraj":"Jihomoravský kraj","obyvatel":1293,"mandatu":15,"okresNuts":"CZ0644","volicu":1036,"ucast":55.98,"platneHlasy":7847,"strany":[{"nazev":"Vinaři - za obec krásnější","hlasy":2328,"mandaty":5,"kandidatu":15},{"nazev":"Zapálení pro Bořetice","hlasy":2792,"mandaty":5,"kandidatu":15},{"nazev":"Za rozvoj Bořetic","hlasy":1540,"mandaty":3,"kandidatu":15},{"nazev":"KDU-ČSL","hlasy":1187,"mandaty":2,"kandidatu":15}]},{"kod":"584355","nazev":"Brod nad Dyjí","okres":"Břeclav","kraj":"Jihomoravský kraj","obyvatel":522,"mandatu":7,"okresNuts":"CZ0644","volicu":454,"ucast":55.07,"platneHlasy":1654,"strany":[{"nazev":"Nezávislí za lepší Brod nad Dyjí","hlasy":745,"mandaty":3,"kandidatu":8},{"nazev":"SNK Brod nad Dyjí","hlasy":909,"mandaty":4,"kandidatu":7}]},{"kod":"584363","nazev":"Brumovice","okres":"Břeclav","kraj":"Jihomoravský kraj","obyvatel":1025,"mandatu":15,"okresNuts":"CZ0644","volicu":788,"ucast":59.9,"platneHlasy":6556,"strany":[{"nazev":"Brumovice pro občany, občané pro Brumovice","hlasy":1295,"mandaty":3,"kandidatu":15},{"nazev":"SDRUŽENÍ NEZÁVISLÝCH KANDIDÁTŮ","hlasy":891,"mandaty":2,"kandidatu":15},{"nazev":"SPOLEK BRUMOVICKÝCH VINAŘŮ","hlasy":860,"mandaty":2,"kandidatu":15},{"nazev":"NEZÁVISLÍ BRUMOVIČTÍ HASIČI","hlasy":3510,"mandaty":8,"kandidatu":15}]},{"kod":"584291","nazev":"Břeclav","okres":"Břeclav","kraj":"Jihomoravský kraj","obyvatel":23943,"mandatu":27,"okresNuts":"CZ0644","volicu":19714,"ucast":40.2,"platneHlasy":192876,"strany":[{"nazev":"MORAVANÉ PRO REGION","hlasy":4410,"mandaty":0,"kandidatu":27},{"nazev":"PŘÍSAHA - občanské hnutí Roberta Šlachty","hlasy":3176,"mandaty":0,"kandidatu":20},{"nazev":"Naše Břeclav","hlasy":18075,"mandaty":3,"kandidatu":27},{"nazev":"Občanská demokratická strana","hlasy":10615,"mandaty":2,"kandidatu":27},{"nazev":"SPD a nezávislí pro Břeclav","hlasy":12704,"mandaty":2,"kandidatu":27},{"nazev":"KSČM a nezávislí","hlasy":9530,"mandaty":0,"kandidatu":27},{"nazev":"ANO 2011","hlasy":52503,"mandaty":9,"kandidatu":27},{"nazev":"Změna pro Břeclav","hlasy":9084,"mandaty":0,"kandidatu":27},{"nazev":"MLADÍ A NEKLIDNÍ BŘECLAV","hlasy":30355,"mandaty":5,"kandidatu":27},{"nazev":"KDU-ČSL","hlasy":10386,"mandaty":1,"kandidatu":27},{"nazev":"Aktivně pro Břeclav","hlasy":3838,"mandaty":0,"kandidatu":27},{"nazev":"Pro Region","hlasy":28200,"mandaty":5,"kandidatu":27}]},{"kod":"584371","nazev":"Březí","okres":"Břeclav","kraj":"Jihomoravský kraj","obyvatel":1696,"mandatu":15,"okresNuts":"CZ0644","volicu":1346,"ucast":59.58,"platneHlasy":11279,"strany":[{"nazev":"BŘEZÍ PRO VŠECHNY","hlasy":1780,"mandaty":2,"kandidatu":15},{"nazev":"PRO OBEC","hlasy":4217,"mandaty":6,"kandidatu":15},{"nazev":"Pro rozvoj obce","hlasy":3574,"mandaty":5,"kandidatu":15},{"nazev":"VAŠE BŘEZÍ","hlasy":1708,"mandaty":2,"kandidatu":15}]},{"kod":"584380","nazev":"Bulhary","okres":"Břeclav","kraj":"Jihomoravský kraj","obyvatel":714,"mandatu":9,"okresNuts":"CZ0644","volicu":613,"ucast":61.83,"platneHlasy":3299,"strany":[{"nazev":"Nezávislí kandidáti Bulhary","hlasy":902,"mandaty":3,"kandidatu":9},{"nazev":"Sdružení nezávislých kandidátů - PRO OBEC BULHARY","hlasy":846,"mandaty":2,"kandidatu":9},{"nazev":"ŽENY PRO BULHARY","hlasy":352,"mandaty":1,"kandidatu":9},{"nazev":"ZMĚNA","hlasy":489,"mandaty":1,"kandidatu":9},{"nazev":"Komunistická strana Čech a Moravy","hlasy":356,"mandaty":1,"kandidatu":9},{"nazev":"KDU-ČSL","hlasy":354,"mandaty":1,"kandidatu":9}]},{"kod":"584401","nazev":"Diváky","okres":"Břeclav","kraj":"Jihomoravský kraj","obyvatel":501,"mandatu":9,"okresNuts":"CZ0644","volicu":400,"ucast":38.5,"platneHlasy":910,"strany":[{"nazev":"Sdružení nezávislých kandidátů Diváky","hlasy":910,"mandaty":9,"kandidatu":9}]},{"kod":"584410","nazev":"Dobré Pole","okres":"Břeclav","kraj":"Jihomoravský kraj","obyvatel":470,"mandatu":7,"okresNuts":"CZ0644","volicu":358,"ucast":64.53,"platneHlasy":1590,"strany":[{"nazev":"Pro DePo","hlasy":417,"mandaty":2,"kandidatu":8},{"nazev":"Za hezčí obec","hlasy":915,"mandaty":4,"kandidatu":9},{"nazev":"Pro blaho všech","hlasy":258,"mandaty":1,"kandidatu":7}]},{"kod":"584428","nazev":"Dolní Dunajovice","okres":"Břeclav","kraj":"Jihomoravský kraj","obyvatel":1694,"mandatu":15,"okresNuts":"CZ0644","volicu":1417,"ucast":38.18,"platneHlasy":6864,"strany":[{"nazev":"OBEC LIDEM","hlasy":1278,"mandaty":3,"kandidatu":15},{"nazev":"Sdružení nezávislých kandidátů 2022","hlasy":2242,"mandaty":5,"kandidatu":15},{"nazev":"SNK 2022","hlasy":1752,"mandaty":4,"kandidatu":15},{"nazev":"SNK 2022 pro rozvoj Dolních Dunajovic","hlasy":1592,"mandaty":3,"kandidatu":15}]},{"kod":"584436","nazev":"Dolní Věstonice","okres":"Břeclav","kraj":"Jihomoravský kraj","obyvatel":292,"mandatu":7,"okresNuts":"CZ0644","volicu":261,"ucast":77.39,"platneHlasy":1321,"strany":[{"nazev":"Vinaři a myslivci Dolní Věstonice","hlasy":63,"mandaty":0,"kandidatu":6},{"nazev":"Za spokojený život","hlasy":124,"mandaty":0,"kandidatu":6},{"nazev":"Za Věstonice","hlasy":69,"mandaty":0,"kandidatu":6},{"nazev":"ZA ZMĚNU","hlasy":182,"mandaty":1,"kandidatu":7},{"nazev":"Věstonický spolek","hlasy":883,"mandaty":6,"kandidatu":7}]},{"kod":"584444","nazev":"Drnholec","okres":"Břeclav","kraj":"Jihomoravský kraj","obyvatel":1834,"mandatu":15,"okresNuts":"CZ0644","volicu":1446,"ucast":44.4,"platneHlasy":8183,"strany":[{"nazev":"Alternativa pro Drnholec","hlasy":3894,"mandaty":7,"kandidatu":15},{"nazev":"DRNHOLEC 2022","hlasy":4289,"mandaty":8,"kandidatu":15}]},{"kod":"584452","nazev":"Hlohovec","okres":"Břeclav","kraj":"Jihomoravský kraj","obyvatel":1289,"mandatu":15,"okresNuts":"CZ0644","volicu":1022,"ucast":50.68,"platneHlasy":6818,"strany":[{"nazev":"Sdružení nezávislých kandidátů","hlasy":2323,"mandaty":5,"kandidatu":15},{"nazev":"Občanská demokratická strana","hlasy":2896,"mandaty":7,"kandidatu":15},{"nazev":"KDU-ČSL","hlasy":1599,"mandaty":3,"kandidatu":15}]},{"kod":"584461","nazev":"Horní Bojanovice","okres":"Břeclav","kraj":"Jihomoravský kraj","obyvatel":664,"mandatu":7,"okresNuts":"CZ0644","volicu":546,"ucast":76.56,"platneHlasy":2833,"strany":[{"nazev":"Nezávislí kandidáti HORNÍCH BOJANOVIC","hlasy":599,"mandaty":1,"kandidatu":7},{"nazev":"Občanská demokratická strana","hlasy":412,"mandaty":1,"kandidatu":7},{"nazev":"HASIČI A ZAHRÁDKÁŘI PRO NAŠI OBEC","hlasy":1363,"mandaty":4,"kandidatu":7},{"nazev":"NAŠE OBEC","hlasy":459,"mandaty":1,"kandidatu":7}]},{"kod":"584479","nazev":"Horní Věstonice","okres":"Břeclav","kraj":"Jihomoravský kraj","obyvatel":496,"mandatu":7,"okresNuts":"CZ0644","volicu":408,"ucast":63.24,"platneHlasy":1724,"strany":[{"nazev":"PRO Horní Věstonice","hlasy":1165,"mandaty":5,"kandidatu":9},{"nazev":"OBČANÉ PRO OBEC","hlasy":559,"mandaty":2,"kandidatu":9}]},{"kod":"584487","nazev":"Hrušky","okres":"Břeclav","kraj":"Jihomoravský kraj","obyvatel":1633,"mandatu":15,"okresNuts":"CZ0644","volicu":1276,"ucast":54.55,"platneHlasy":9300,"strany":[{"nazev":"Prosperita pro Hrušky","hlasy":2205,"mandaty":3,"kandidatu":15},{"nazev":"Pro lepší Hrušky","hlasy":1767,"mandaty":3,"kandidatu":14},{"nazev":"KDU-ČSL","hlasy":4522,"mandaty":8,"kandidatu":15},{"nazev":"Komunistická strana Čech a Moravy","hlasy":806,"mandaty":1,"kandidatu":12}]},{"kod":"584495","nazev":"Hustopeče","okres":"Břeclav","kraj":"Jihomoravský kraj","obyvatel":5998,"mandatu":21,"okresNuts":"CZ0644","volicu":4827,"ucast":45.99,"platneHlasy":42282,"strany":[{"nazev":"Česká strana sociálně demokratická","hlasy":3128,"mandaty":1,"kandidatu":21},{"nazev":"Občanská demokratická strana","hlasy":5549,"mandaty":3,"kandidatu":21},{"nazev":"ZDRAVÉ HUSTOPEČE","hlasy":7549,"mandaty":4,"kandidatu":21},{"nazev":"KDU-ČSL","hlasy":5827,"mandaty":3,"kandidatu":21},{"nazev":"Sdružení nestraníků","hlasy":11050,"mandaty":6,"kandidatu":21},{"nazev":"NEZÁVISLÍ","hlasy":9179,"mandaty":4,"kandidatu":21}]},{"kod":"584525","nazev":"Jevišovka","okres":"Břeclav","kraj":"Jihomoravský kraj","obyvatel":664,"mandatu":7,"okresNuts":"CZ0644","volicu":523,"ucast":25.24,"platneHlasy":690,"strany":[{"nazev":"Sdružení nezávislých kandidátů 2022","hlasy":690,"mandaty":7,"kandidatu":8}]},{"kod":"550256","nazev":"Kašnice","okres":"Břeclav","kraj":"Jihomoravský kraj","obyvatel":206,"mandatu":5,"okresNuts":"CZ0644","volicu":177,"ucast":48.02,"platneHlasy":286,"strany":[{"nazev":"Bc. Miroslava Šimoníková","hlasy":58,"mandaty":1,"kandidatu":1},{"nazev":"Ing. Jana Majerová","hlasy":69,"mandaty":1,"kandidatu":1},{"nazev":"Mgr. Pavel Zvonař","hlasy":48,"mandaty":1,"kandidatu":1},{"nazev":"Ing. Radek Kocman","hlasy":48,"mandaty":1,"kandidatu":1},{"nazev":"Ing. Tomáš Rozbořil","hlasy":63,"mandaty":1,"kandidatu":1}]},{"kod":"584541","nazev":"Klentnice","okres":"Břeclav","kraj":"Jihomoravský kraj","obyvatel":488,"mandatu":7,"okresNuts":"CZ0644","volicu":407,"ucast":60.2,"platneHlasy":1634,"strany":[{"nazev":"Česká strana sociálně demokratická","hlasy":538,"mandaty":2,"kandidatu":9},{"nazev":"22plus pro Klentnici","hlasy":731,"mandaty":4,"kandidatu":9},{"nazev":"KDU-ČSL","hlasy":148,"mandaty":0,"kandidatu":8},{"nazev":"VÍCE PRO KLENTNICI","hlasy":217,"mandaty":1,"kandidatu":7}]},{"kod":"584550","nazev":"Klobouky u Brna","okres":"Břeclav","kraj":"Jihomoravský kraj","obyvatel":2426,"mandatu":15,"okresNuts":"CZ0644","volicu":1902,"ucast":50.32,"platneHlasy":12035,"strany":[{"nazev":"Starostové a osobnosti pro Moravu","hlasy":5429,"mandaty":7,"kandidatu":15},{"nazev":"KDU-ČSL","hlasy":2716,"mandaty":3,"kandidatu":15},{"nazev":"ANO 2011","hlasy":3890,"mandaty":5,"kandidatu":15}]},{"kod":"584568","nazev":"Kobylí","okres":"Břeclav","kraj":"Jihomoravský kraj","obyvatel":1966,"mandatu":15,"okresNuts":"CZ0644","volicu":1632,"ucast":52.88,"platneHlasy":11821,"strany":[{"nazev":"KDU-ČSL","hlasy":2475,"mandaty":3,"kandidatu":15},{"nazev":"ANO 2011","hlasy":2558,"mandaty":3,"kandidatu":15},{"nazev":"Nezávislí 2022","hlasy":6788,"mandaty":9,"kandidatu":15}]},{"kod":"584576","nazev":"Kostice","okres":"Břeclav","kraj":"Jihomoravský kraj","obyvatel":1867,"mandatu":15,"okresNuts":"CZ0644","volicu":1566,"ucast":57.15,"platneHlasy":12980,"strany":[{"nazev":"Nezávislí","hlasy":2162,"mandaty":2,"kandidatu":15},{"nazev":"Komunistická strana Čech a Moravy","hlasy":2172,"mandaty":2,"kandidatu":15},{"nazev":"PROKOSTICE","hlasy":8646,"mandaty":11,"kandidatu":15}]},{"kod":"584584","nazev":"Krumvíř","okres":"Břeclav","kraj":"Jihomoravský kraj","obyvatel":1230,"mandatu":15,"okresNuts":"CZ0644","volicu":988,"ucast":52.43,"platneHlasy":7172,"strany":[{"nazev":"Sdružení nezávislých kandidátů","hlasy":5015,"mandaty":11,"kandidatu":15},{"nazev":"Spolu za Krumvíř","hlasy":2157,"mandaty":4,"kandidatu":15}]},{"kod":"584592","nazev":"Křepice","okres":"Břeclav","kraj":"Jihomoravský kraj","obyvatel":1305,"mandatu":15,"okresNuts":"CZ0644","volicu":1063,"ucast":50.52,"platneHlasy":6944,"strany":[{"nazev":"Hasiči Křepice","hlasy":2518,"mandaty":6,"kandidatu":15},{"nazev":"KDU-ČSL","hlasy":1205,"mandaty":2,"kandidatu":15},{"nazev":"Sdružení pro Křepice","hlasy":1329,"mandaty":3,"kandidatu":15},{"nazev":"Sdružení nezávislých kandidátů za TJ Sokol Křepice z.s.","hlasy":1892,"mandaty":4,"kandidatu":15}]},{"kod":"555282","nazev":"Kurdějov","okres":"Břeclav","kraj":"Jihomoravský kraj","obyvatel":440,"mandatu":9,"okresNuts":"CZ0644","volicu":341,"ucast":78.59,"platneHlasy":2240,"strany":[{"nazev":"KDU-ČSL A NEZÁVISLÍ KANDIDÁTI","hlasy":282,"mandaty":1,"kandidatu":9},{"nazev":"Srdce pro Kurdějov","hlasy":359,"mandaty":1,"kandidatu":9},{"nazev":"Sdružení Kurdějovských občanů","hlasy":1018,"mandaty":5,"kandidatu":9},{"nazev":"Změna pro Kurdějov","hlasy":271,"mandaty":1,"kandidatu":9},{"nazev":"Sdružení nezávislých kandidátů","hlasy":310,"mandaty":1,"kandidatu":9}]},{"kod":"558443","nazev":"Ladná","okres":"Břeclav","kraj":"Jihomoravský kraj","obyvatel":1225,"mandatu":9,"okresNuts":"CZ0644","volicu":1027,"ucast":51.8,"platneHlasy":4348,"strany":[{"nazev":"KDU-ČSL","hlasy":1209,"mandaty":2,"kandidatu":9},{"nazev":"Sdružení občanů Ladné","hlasy":3139,"mandaty":7,"kandidatu":9}]},{"kod":"584622","nazev":"Lanžhot","okres":"Břeclav","kraj":"Jihomoravský kraj","obyvatel":3608,"mandatu":21,"okresNuts":"CZ0644","volicu":2982,"ucast":42.86,"platneHlasy":24038,"strany":[{"nazev":"Prosperita, sport a tradice - sdružení nezávislých kandidátů s podporou ČSSD","hlasy":4455,"mandaty":4,"kandidatu":21},{"nazev":"Sdružení nezávislých kandidátů - Změna 2014","hlasy":3027,"mandaty":2,"kandidatu":21},{"nazev":"Volba pro Lanžhot","hlasy":14049,"mandaty":13,"kandidatu":21},{"nazev":"KDU-ČSL","hlasy":2507,"mandaty":2,"kandidatu":21}]},{"kod":"584631","nazev":"Lednice","okres":"Břeclav","kraj":"Jihomoravský kraj","obyvatel":2145,"mandatu":15,"okresNuts":"CZ0644","volicu":1745,"ucast":60.06,"platneHlasy":14748,"strany":[{"nazev":"LEDNICKÉ SDRUŽENÍ DEMOKRATŮ","hlasy":2018,"mandaty":2,"kandidatu":15},{"nazev":"KDU-ČSL","hlasy":1566,"mandaty":2,"kandidatu":15},{"nazev":"ANO 2011","hlasy":1055,"mandaty":1,"kandidatu":15},{"nazev":"Změna pro Lednici","hlasy":376,"mandaty":0,"kandidatu":15},{"nazev":"Soukromníci - Ledničané a Nejdečané","hlasy":1008,"mandaty":1,"kandidatu":15},{"nazev":"Okrašlovací spolek Lednice","hlasy":1544,"mandaty":1,"kandidatu":15},{"nazev":"Moravané","hlasy":720,"mandaty":0,"kandidatu":15},{"nazev":"Sdružení nezávislých","hlasy":3860,"mandaty":5,"kandidatu":15},{"nazev":"PŘÍSAHA - občanské hnutí Roberta Šlachty","hlasy":800,"mandaty":1,"kandidatu":15},{"nazev":"PRO Lednici","hlasy":1801,"mandaty":2,"kandidatu":15}]},{"kod":"584649","nazev":"Mikulov","okres":"Břeclav","kraj":"Jihomoravský kraj","obyvatel":7427,"mandatu":25,"okresNuts":"CZ0644","volicu":5908,"ucast":45.68,"platneHlasy":60788,"strany":[{"nazev":"Komunistická strana Čech a Moravy","hlasy":7680,"mandaty":3,"kandidatu":25},{"nazev":"STAROSTOVÉ A NEZÁVISLÍ","hlasy":5398,"mandaty":2,"kandidatu":25},{"nazev":"ANO 2011","hlasy":14467,"mandaty":7,"kandidatu":25},{"nazev":"Mikulovští","hlasy":12965,"mandaty":6,"kandidatu":25},{"nazev":"Česká pirátská strana","hlasy":5076,"mandaty":2,"kandidatu":25},{"nazev":"Česká strana sociálně demokratická","hlasy":3634,"mandaty":1,"kandidatu":25},{"nazev":"Občanská demokratická strana","hlasy":5806,"mandaty":3,"kandidatu":25},{"nazev":"KDU-ČSL","hlasy":2287,"mandaty":0,"kandidatu":25},{"nazev":"PŘÍSAHA - občanské hnutí Roberta Šlachty","hlasy":3475,"mandaty":1,"kandidatu":25}]},{"kod":"584657","nazev":"Milovice","okres":"Břeclav","kraj":"Jihomoravský kraj","obyvatel":480,"mandatu":7,"okresNuts":"CZ0644","volicu":383,"ucast":55.87,"platneHlasy":1062,"strany":[{"nazev":"Sdružení nezávislých kandidátů","hlasy":1062,"mandaty":7,"kandidatu":9}]},{"kod":"584665","nazev":"Moravská Nová Ves","okres":"Břeclav","kraj":"Jihomoravský kraj","obyvatel":2564,"mandatu":15,"okresNuts":"CZ0644","volicu":2083,"ucast":54.39,"platneHlasy":15509,"strany":[{"nazev":"ANO 2011","hlasy":2001,"mandaty":2,"kandidatu":15},{"nazev":"SPD a nezávislí pro Moravskou Novou Ves","hlasy":380,"mandaty":0,"kandidatu":7},{"nazev":"SPOLEČNĚ A ZODPOVĚDNĚ","hlasy":3205,"mandaty":4,"kandidatu":15},{"nazev":"Nezávislí kandidáti za lepší Moravskou","hlasy":2274,"mandaty":2,"kandidatu":15},{"nazev":"PROSPERUJÍCÍ MORAVSKÁ","hlasy":2607,"mandaty":3,"kandidatu":15},{"nazev":"Komunistická strana Čech a Moravy","hlasy":372,"mandaty":0,"kandidatu":15},{"nazev":"Volba pro obec","hlasy":1039,"mandaty":1,"kandidatu":15},{"nazev":"SÍLA K OBNOVĚ","hlasy":2055,"mandaty":2,"kandidatu":15},{"nazev":"KDU-ČSL","hlasy":1576,"mandaty":1,"kandidatu":15}]},{"kod":"584673","nazev":"Moravský Žižkov","okres":"Břeclav","kraj":"Jihomoravský kraj","obyvatel":1458,"mandatu":15,"okresNuts":"CZ0644","volicu":1185,"ucast":53,"platneHlasy":8863,"strany":[{"nazev":"SNK - ZMĚNA","hlasy":6302,"mandaty":11,"kandidatu":15},{"nazev":"KDU-ČSL","hlasy":1767,"mandaty":3,"kandidatu":15},{"nazev":"Občanská demokratická strana","hlasy":794,"mandaty":1,"kandidatu":14}]},{"kod":"584681","nazev":"Morkůvky","okres":"Břeclav","kraj":"Jihomoravský kraj","obyvatel":522,"mandatu":9,"okresNuts":"CZ0644","volicu":398,"ucast":68.59,"platneHlasy":2337,"strany":[{"nazev":"Sdružení nezávislých kandidátů","hlasy":1382,"mandaty":5,"kandidatu":9},{"nazev":"\"Pro Morkůvky\"","hlasy":955,"mandaty":4,"kandidatu":9}]},{"kod":"584703","nazev":"Němčičky","okres":"Břeclav","kraj":"Jihomoravský kraj","obyvatel":703,"mandatu":9,"okresNuts":"CZ0644","volicu":568,"ucast":64.44,"platneHlasy":3136,"strany":[{"nazev":"Naše Němčičky","hlasy":642,"mandaty":2,"kandidatu":9},{"nazev":"KDU-ČSL","hlasy":377,"mandaty":1,"kandidatu":9},{"nazev":"Občanská demokratická strana","hlasy":726,"mandaty":2,"kandidatu":9},{"nazev":"SDRUŽENÍ NEZÁVISLÝCH KANDIDÁTŮ NĚMČIČKY","hlasy":1391,"mandaty":4,"kandidatu":9}]},{"kod":"584711","nazev":"Nikolčice","okres":"Břeclav","kraj":"Jihomoravský kraj","obyvatel":771,"mandatu":7,"okresNuts":"CZ0644","volicu":630,"ucast":70,"platneHlasy":2926,"strany":[{"nazev":"NEZÁVISLÍ NIKOLČICE","hlasy":1444,"mandaty":4,"kandidatu":7},{"nazev":"KDU-ČSL","hlasy":670,"mandaty":1,"kandidatu":7},{"nazev":"Pro lepší budoucnost našich dětí","hlasy":405,"mandaty":1,"kandidatu":7},{"nazev":"VĚCI SPOLEČNÉ","hlasy":407,"mandaty":1,"kandidatu":7}]},{"kod":"584746","nazev":"Novosedly","okres":"Břeclav","kraj":"Jihomoravský kraj","obyvatel":1278,"mandatu":15,"okresNuts":"CZ0644","volicu":1000,"ucast":41.6,"platneHlasy":5218,"strany":[{"nazev":"PRO Novosedly","hlasy":4381,"mandaty":13,"kandidatu":15},{"nazev":"Občanská demokratická strana","hlasy":837,"mandaty":2,"kandidatu":15}]},{"kod":"584754","nazev":"Nový Přerov","okres":"Břeclav","kraj":"Jihomoravský kraj","obyvatel":348,"mandatu":7,"okresNuts":"CZ0644","volicu":286,"ucast":61.19,"platneHlasy":1155,"strany":[{"nazev":"NOVÝ SMĚR","hlasy":381,"mandaty":2,"kandidatu":9},{"nazev":"Moderní obec","hlasy":283,"mandaty":2,"kandidatu":9},{"nazev":"Patrioti pro Nový Přerov","hlasy":140,"mandaty":1,"kandidatu":9},{"nazev":"Vraťme obec občanům","hlasy":351,"mandaty":2,"kandidatu":9}]},{"kod":"584771","nazev":"Pavlov","okres":"Břeclav","kraj":"Jihomoravský kraj","obyvatel":583,"mandatu":7,"okresNuts":"CZ0644","volicu":450,"ucast":60,"platneHlasy":1759,"strany":[{"nazev":"PRO BUDOUCNOST PAVLOVA","hlasy":231,"mandaty":1,"kandidatu":9},{"nazev":"SDRUŽENÍ NEZÁVISLÝCH KANDIDÁTŮ ZA MODERNÍ PAVLOV","hlasy":243,"mandaty":1,"kandidatu":9},{"nazev":"PRO OBEC PAVLOV","hlasy":614,"mandaty":3,"kandidatu":9},{"nazev":"Česká strana sociálně demokratická a nezávislí kandidáti","hlasy":373,"mandaty":1,"kandidatu":9},{"nazev":"Občanská demokratická strana","hlasy":298,"mandaty":1,"kandidatu":7}]},{"kod":"584789","nazev":"Perná","okres":"Břeclav","kraj":"Jihomoravský kraj","obyvatel":797,"mandatu":7,"okresNuts":"CZ0644","volicu":645,"ucast":50.23,"platneHlasy":1965,"strany":[{"nazev":"KDU-ČSL","hlasy":584,"mandaty":2,"kandidatu":7},{"nazev":"Sdružení pro kulturu a sport","hlasy":905,"mandaty":3,"kandidatu":9},{"nazev":"Sdružení nezávislých kandidátů Perná","hlasy":476,"mandaty":2,"kandidatu":7}]},{"kod":"584797","nazev":"Podivín","okres":"Břeclav","kraj":"Jihomoravský kraj","obyvatel":2954,"mandatu":15,"okresNuts":"CZ0644","volicu":2355,"ucast":45.27,"platneHlasy":14119,"strany":[{"nazev":"Komunistická strana Čech a Moravy","hlasy":1920,"mandaty":2,"kandidatu":15},{"nazev":"Sdružení nezávislých kandidátů ZA PODIVÍN - ZA KRÁSNĚJŠÍ PODIVÍN","hlasy":4024,"mandaty":4,"kandidatu":13},{"nazev":"Občanská demokratická strana","hlasy":5117,"mandaty":6,"kandidatu":15},{"nazev":"NESTRANÍCI","hlasy":1054,"mandaty":1,"kandidatu":14},{"nazev":"KDU-ČSL","hlasy":2004,"mandaty":2,"kandidatu":15}]},{"kod":"584819","nazev":"Popice","okres":"Břeclav","kraj":"Jihomoravský kraj","obyvatel":981,"mandatu":11,"okresNuts":"CZ0644","volicu":763,"ucast":55.05,"platneHlasy":4143,"strany":[{"nazev":"KDU-ČSL","hlasy":1255,"mandaty":3,"kandidatu":11},{"nazev":"Sdružení nezávislých kandidátů za rozvoj obce a sportu","hlasy":2888,"mandaty":8,"kandidatu":11}]},{"kod":"584835","nazev":"Pouzdřany","okres":"Břeclav","kraj":"Jihomoravský kraj","obyvatel":789,"mandatu":9,"okresNuts":"CZ0644","volicu":636,"ucast":41.82,"platneHlasy":2154,"strany":[{"nazev":"Moravané","hlasy":641,"mandaty":3,"kandidatu":9},{"nazev":"PŘÍSAHA - občanské hnutí Roberta Šlachty","hlasy":1165,"mandaty":5,"kandidatu":9},{"nazev":"Komunistická strana Čech a Moravy","hlasy":348,"mandaty":1,"kandidatu":9}]},{"kod":"584851","nazev":"Přítluky","okres":"Břeclav","kraj":"Jihomoravský kraj","obyvatel":756,"mandatu":9,"okresNuts":"CZ0644","volicu":641,"ucast":49.14,"platneHlasy":2566,"strany":[{"nazev":"SPOLEČNĚ PRO PŘÍTLUKY","hlasy":1000,"mandaty":3,"kandidatu":9},{"nazev":"NADĚJE 2022","hlasy":540,"mandaty":2,"kandidatu":9},{"nazev":"SDRUŽENÍ NEZÁVISLÝCH KANDIDÁTŮ","hlasy":1026,"mandaty":4,"kandidatu":9}]},{"kod":"584860","nazev":"Rakvice","okres":"Břeclav","kraj":"Jihomoravský kraj","obyvatel":2162,"mandatu":9,"okresNuts":"CZ0644","volicu":1755,"ucast":46.78,"platneHlasy":6667,"strany":[{"nazev":"PRO LEPŠÍ RAKVICE","hlasy":1267,"mandaty":2,"kandidatu":9},{"nazev":"Občanská demokratická strana","hlasy":2234,"mandaty":3,"kandidatu":9},{"nazev":"Společně pro Rakvice","hlasy":1494,"mandaty":2,"kandidatu":9},{"nazev":"ŽIVÉ RAKVICE","hlasy":1672,"mandaty":2,"kandidatu":9}]},{"kod":"584878","nazev":"Sedlec","okres":"Břeclav","kraj":"Jihomoravský kraj","obyvatel":854,"mandatu":7,"okresNuts":"CZ0644","volicu":701,"ucast":53.21,"platneHlasy":2239,"strany":[{"nazev":"Obec pro každého","hlasy":1869,"mandaty":6,"kandidatu":8},{"nazev":"JAN VAŇKÁT","hlasy":45,"mandaty":0,"kandidatu":1},{"nazev":"Levice pro Sedlec","hlasy":325,"mandaty":1,"kandidatu":7}]},{"kod":"584894","nazev":"Starovice","okres":"Břeclav","kraj":"Jihomoravský kraj","obyvatel":911,"mandatu":9,"okresNuts":"CZ0644","volicu":723,"ucast":38.17,"platneHlasy":1555,"strany":[{"nazev":"PRO NAŠE STAROVICE","hlasy":1555,"mandaty":9,"kandidatu":9}]},{"kod":"584908","nazev":"Starovičky","okres":"Břeclav","kraj":"Jihomoravský kraj","obyvatel":904,"mandatu":9,"okresNuts":"CZ0644","volicu":692,"ucast":58.24,"platneHlasy":3336,"strany":[{"nazev":"NÁŠ VENKOV II.","hlasy":120,"mandaty":0,"kandidatu":7},{"nazev":"NÁŠ VENKOV I.","hlasy":648,"mandaty":2,"kandidatu":9},{"nazev":"NEZÁVISLÍ ZA NAŠI OBEC","hlasy":549,"mandaty":1,"kandidatu":9},{"nazev":"Strana nezávislých","hlasy":1539,"mandaty":5,"kandidatu":9},{"nazev":"Strana nezávislých kandidátů","hlasy":480,"mandaty":1,"kandidatu":9}]},{"kod":"584916","nazev":"Strachotín","okres":"Břeclav","kraj":"Jihomoravský kraj","obyvatel":794,"mandatu":7,"okresNuts":"CZ0644","volicu":661,"ucast":61.72,"platneHlasy":2682,"strany":[{"nazev":"Strachotín 2022","hlasy":521,"mandaty":1,"kandidatu":7},{"nazev":"NEZÁVISLÍ 2022","hlasy":359,"mandaty":1,"kandidatu":7},{"nazev":"Mladí pro Strachotín 2022","hlasy":297,"mandaty":1,"kandidatu":9},{"nazev":"Pro Strachotín 2022","hlasy":257,"mandaty":0,"kandidatu":9},{"nazev":"STAROSTOVÉ A NEZÁVISLÍ","hlasy":825,"mandaty":3,"kandidatu":7},{"nazev":"Komunistická strana Čech a Moravy","hlasy":423,"mandaty":1,"kandidatu":7}]},{"kod":"584924","nazev":"Šakvice","okres":"Břeclav","kraj":"Jihomoravský kraj","obyvatel":1494,"mandatu":9,"okresNuts":"CZ0644","volicu":1198,"ucast":24.96,"platneHlasy":1395,"strany":[{"nazev":"STAROSTOVÉ A NEZÁVISLÍ","hlasy":1395,"mandaty":9,"kandidatu":9}]},{"kod":"584932","nazev":"Šitbořice","okres":"Břeclav","kraj":"Jihomoravský kraj","obyvatel":2095,"mandatu":15,"okresNuts":"CZ0644","volicu":1637,"ucast":34.64,"platneHlasy":5717,"strany":[{"nazev":"KDU-ČSL","hlasy":5543,"mandaty":15,"kandidatu":15},{"nazev":"Ing. Pavel Halas","hlasy":174,"mandaty":0,"kandidatu":1}]},{"kod":"584941","nazev":"Tvrdonice","okres":"Břeclav","kraj":"Jihomoravský kraj","obyvatel":2079,"mandatu":15,"okresNuts":"CZ0644","volicu":1678,"ucast":55.18,"platneHlasy":12533,"strany":[{"nazev":"NADĚJE PRO RODINU","hlasy":1009,"mandaty":1,"kandidatu":15},{"nazev":"PRO LEPŠÍ TVRDONICE","hlasy":1573,"mandaty":2,"kandidatu":15},{"nazev":"SPOLEČNĚ PRO TVRDONICE","hlasy":2715,"mandaty":4,"kandidatu":15},{"nazev":"KDU-ČSL","hlasy":2019,"mandaty":2,"kandidatu":15},{"nazev":"Sdružení nezávislých kandidátů","hlasy":1410,"mandaty":2,"kandidatu":15},{"nazev":"Občanská demokratická strana","hlasy":997,"mandaty":1,"kandidatu":15},{"nazev":"Komunistická strana Čech a Moravy","hlasy":818,"mandaty":1,"kandidatu":15},{"nazev":"PRO TVRDONICE","hlasy":1992,"mandaty":2,"kandidatu":15}]},{"kod":"584959","nazev":"Týnec","okres":"Břeclav","kraj":"Jihomoravský kraj","obyvatel":1086,"mandatu":15,"okresNuts":"CZ0644","volicu":874,"ucast":56.41,"platneHlasy":6809,"strany":[{"nazev":"Komunistická strana Čech a Moravy","hlasy":938,"mandaty":2,"kandidatu":15},{"nazev":"SDRUŽENÍ NEZÁVISLÝCH KANDIDÁTŮ","hlasy":888,"mandaty":2,"kandidatu":15},{"nazev":"KDU-ČSL","hlasy":693,"mandaty":1,"kandidatu":15},{"nazev":"Týnecká dědina","hlasy":747,"mandaty":1,"kandidatu":15},{"nazev":"Společně pro Týnec","hlasy":2746,"mandaty":7,"kandidatu":15},{"nazev":"NÁŠ TÝNEC 2022","hlasy":797,"mandaty":2,"kandidatu":15}]},{"kod":"584967","nazev":"Uherčice","okres":"Břeclav","kraj":"Jihomoravský kraj","obyvatel":1073,"mandatu":15,"okresNuts":"CZ0644","volicu":851,"ucast":69.1,"platneHlasy":8297,"strany":[{"nazev":"Nezávislí kandidáti","hlasy":4354,"mandaty":8,"kandidatu":15},{"nazev":"Změna pro Uherčice","hlasy":2439,"mandaty":4,"kandidatu":15},{"nazev":"KDU-ČSL","hlasy":1504,"mandaty":3,"kandidatu":15}]},{"kod":"584975","nazev":"Valtice","okres":"Břeclav","kraj":"Jihomoravský kraj","obyvatel":3488,"mandatu":15,"okresNuts":"CZ0644","volicu":2904,"ucast":45.97,"platneHlasy":18427,"strany":[{"nazev":"ANO 2011","hlasy":1880,"mandaty":1,"kandidatu":15},{"nazev":"KDU-ČSL","hlasy":1581,"mandaty":1,"kandidatu":15},{"nazev":"Volba pro Valtice","hlasy":2346,"mandaty":2,"kandidatu":15},{"nazev":"ZMĚNA 22","hlasy":3085,"mandaty":3,"kandidatu":15},{"nazev":"VALTIČANÉ 2018","hlasy":3919,"mandaty":4,"kandidatu":15},{"nazev":"OBCHVAT PRO VALTICE","hlasy":805,"mandaty":0,"kandidatu":15},{"nazev":"Komunistická strana Čech a Moravy","hlasy":452,"mandaty":0,"kandidatu":15},{"nazev":"PŘÍSAHA - občanské hnutí Roberta Šlachty","hlasy":354,"mandaty":0,"kandidatu":15},{"nazev":"Česká strana sociálně demokratická a nezávislí kandidáti","hlasy":2060,"mandaty":2,"kandidatu":15},{"nazev":"Občanská demokratická strana","hlasy":1945,"mandaty":2,"kandidatu":15}]},{"kod":"584983","nazev":"Velké Bílovice","okres":"Břeclav","kraj":"Jihomoravský kraj","obyvatel":3818,"mandatu":15,"okresNuts":"CZ0644","volicu":3081,"ucast":43.36,"platneHlasy":17400,"strany":[{"nazev":"KDU-ČSL","hlasy":5868,"mandaty":5,"kandidatu":15},{"nazev":"NEZÁVISLÍ KANDIDÁTI","hlasy":11532,"mandaty":10,"kandidatu":15}]},{"kod":"584991","nazev":"Velké Hostěrádky","okres":"Břeclav","kraj":"Jihomoravský kraj","obyvatel":500,"mandatu":9,"okresNuts":"CZ0644","volicu":387,"ucast":65.37,"platneHlasy":2112,"strany":[{"nazev":"Moravané","hlasy":601,"mandaty":2,"kandidatu":9},{"nazev":"Sdružení nezávislých kandidátů","hlasy":1511,"mandaty":7,"kandidatu":9}]},{"kod":"585009","nazev":"Velké Němčice","okres":"Břeclav","kraj":"Jihomoravský kraj","obyvatel":1759,"mandatu":15,"okresNuts":"CZ0644","volicu":1429,"ucast":59.34,"platneHlasy":11870,"strany":[{"nazev":"Budoucnost Velkých Němčic","hlasy":3413,"mandaty":4,"kandidatu":15},{"nazev":"KDU-ČSL","hlasy":2732,"mandaty":4,"kandidatu":15},{"nazev":"HASIČI VELKÉ NĚMČICE","hlasy":1358,"mandaty":1,"kandidatu":15},{"nazev":"Sdružení nezávislých kandidátů TJ Sokol Velké Němčice","hlasy":1453,"mandaty":2,"kandidatu":15},{"nazev":"VELKÉ NĚMČICE 2022","hlasy":2914,"mandaty":4,"kandidatu":15}]},{"kod":"585017","nazev":"Velké Pavlovice","okres":"Břeclav","kraj":"Jihomoravský kraj","obyvatel":3052,"mandatu":15,"okresNuts":"CZ0644","volicu":2477,"ucast":56.24,"platneHlasy":19280,"strany":[{"nazev":"#nejenHASICIVP","hlasy":4573,"mandaty":4,"kandidatu":15},{"nazev":"Velkopavlovičtí nezávislí","hlasy":3893,"mandaty":3,"kandidatu":15},{"nazev":"Koalice ODS a KDU-ČSL","hlasy":1805,"mandaty":1,"kandidatu":15},{"nazev":"Patrioti Velkých Pavlovic","hlasy":4942,"mandaty":4,"kandidatu":15},{"nazev":"SNK Pro rozvoj Velkých Pavlovic","hlasy":2951,"mandaty":2,"kandidatu":15},{"nazev":"Komunistická strana Čech a Moravy","hlasy":1116,"mandaty":1,"kandidatu":15}]},{"kod":"585041","nazev":"Vrbice","okres":"Břeclav","kraj":"Jihomoravský kraj","obyvatel":1050,"mandatu":9,"okresNuts":"CZ0644","volicu":864,"ucast":64.93,"platneHlasy":4804,"strany":[{"nazev":"Lidé Vrbice","hlasy":2006,"mandaty":4,"kandidatu":9},{"nazev":"Za Vrbici ještě krásnější","hlasy":2798,"mandaty":5,"kandidatu":9}]},{"kod":"585050","nazev":"Zaječí","okres":"Břeclav","kraj":"Jihomoravský kraj","obyvatel":1492,"mandatu":15,"okresNuts":"CZ0644","volicu":1209,"ucast":48.14,"platneHlasy":7667,"strany":[{"nazev":"Nezávislí pro Zaječí","hlasy":4660,"mandaty":10,"kandidatu":15},{"nazev":"Fórum Zaječí","hlasy":1370,"mandaty":2,"kandidatu":15},{"nazev":"Sdružení nezávislých kandidátů a ODS Zaječí","hlasy":1637,"mandaty":3,"kandidatu":15}]}]